{"kind":"tdf-color","format":"tdf-compact-v1","key":"fields.tdf","name":"Fields","height":7,"spacing":2,"colorSlots":["0x01","0x02","0x07","0x09","0x12","0x17","0x19","0x1e","0x20","0x28","0x2c","0x4c"],"glyphs":{"A":{"chars":["‚ĖĄ ‚Ėą‚Ėą‚Ėą‚Ėą‚ĖÄ ‚Ėą‚ĖÄ‚Ėą‚Ėą‚ĖĄ","‚Ėą‚Ėą‚Ėą‚Ėą‚Ėą‚Ėą ‚Ėą‚Ėą‚Ėą‚ĖĄ‚ĖÄ‚Ėą","‚Ėą‚Ėą‚Ėą‚Ėą ‚Ėą‚ĖĄ‚Ėą‚Ėą‚Ė† ‚Ėą‚ĖĄ","‚ĖĄ‚ĖĄ‚ĖĄ‚ĖĄ‚ĖĄ‚ĖĄ ‚ĖĄ ‚ĖÄ‚ĖÄ‚ĖÄ‚ĖÄ","‚Ėą‚Ėą‚ĖĄ‚Ėą‚Ėą‚Ėą ‚Ėą‚Ėą‚Ėą‚Ėą‚Ėą‚Ėą","‚Ėą‚ĖÄ‚ĖĄ‚ĖÄ‚Ėą‚Ėą ‚Ėą‚ĖĄ‚ĖÄ‚ĖĄ‚Ėą‚Ėą","‚Ėą‚Ėą‚Ėą‚Ėą‚Ėą‚Ėą ‚Ėą‚Ėą‚ĖÄ‚Ėą‚Ėą‚Ėą"],"colors":["011e01010101011e0119190909","01010101010107010101191919","010101011e01010101191e0119","02020202020207020701010101","02022c02020207020202020212","022c4c2c020207022c4c2c0202","0202020202020702022c020202"]},"B":{"chars":["‚Ėą ‚Ėą‚Ėą‚Ėą‚Ėą‚ĖÄ ‚Ėą‚ĖÄ‚Ėą‚Ėą‚ĖĄ","‚Ėą‚Ėą‚Ėą‚Ėą‚Ėą‚Ėą ‚Ėą‚Ėą‚Ėą‚ĖĄ‚ĖÄ‚ĖÄ","‚Ėą‚Ėą‚Ėą‚Ėą ‚Ėą‚ĖĄ‚Ėą‚Ėą‚Ė† ‚ĖĄ ","‚ĖĄ‚ĖĄ‚ĖĄ‚ĖĄ‚ĖĄ‚ĖĄ ‚ĖĄ ‚ĖÄ‚ĖÄ‚ĖÄ‚ĖÄ","‚Ėą‚Ėą‚ĖĄ‚Ėą‚Ėą‚Ėą ‚Ėą‚Ėą‚Ėą‚Ėą‚Ėą‚Ėą","‚Ėą‚ĖÄ‚ĖĄ‚ĖÄ‚Ėą‚Ėą ‚Ėą‚ĖĄ‚ĖÄ‚ĖĄ‚Ėą‚Ėą","‚Ėą‚Ėą‚Ėą‚Ėą‚Ėą‚Ėą‚ĖĄ‚Ėą‚Ėą‚ĖÄ‚Ėą‚Ėą‚ĖÄ"],"colors":["011e01010101011e0119190909","01010101010107010101191901","010101011e01010101191e0107","02020202020207020701010101","02022c02020207020202020212","022c4c2c020207022c4c2c0202","0202020202020202022c020202"]},"C":{"chars":["‚ĖĄ    ‚Ėą‚ĖÄ‚Ėą‚Ėą‚Ėą‚Ė†‚ĖÄ‚Ėą"," ‚Ėą‚Ėą‚Ėą‚Ėą‚Ėą ‚Ėą‚Ėą‚Ėą‚Ėą‚Ėą‚Ėą","‚Ėą‚Ėą‚Ėą‚Ėą‚Ėą‚Ėą ‚ĖÄ‚ĖÄ‚ĖÄ‚ĖÄ‚ĖÄ‚ĖÄ","‚ĖĄ‚ĖĄ‚ĖĄ ‚ĖÄ‚ĖÄ       ","‚Ėą‚Ėą‚Ėą‚Ėą‚ĖĄ‚Ėą ‚Ėą‚Ėą‚Ėą‚ĖÄ‚ĖĄ‚ĖÄ","‚Ėą‚Ėą‚Ėą‚ĖÄ‚ĖĄ‚ĖÄ ‚Ėą‚Ėą‚Ėą‚Ėą‚Ėą‚Ėą","‚ĖÄ‚Ėą‚Ėą‚Ėą‚Ėą‚Ėą‚ĖĄ‚Ėą‚Ėą‚Ėą‚Ėą‚Ėą‚ĖÄ"],"colors":["01191919190101010101191919","17010101010107010101010101","01010101010107010101010101","02020207010107070707070707","020202022c02070202022c4c2c","0202022c4c2c07020202020202","02020202020202020202020202"]},"D":{"chars":["‚Ėą ‚Ėą‚Ėą‚Ėą‚Ėą‚ĖÄ ‚Ėą‚ĖÄ‚Ėą‚Ėą‚ĖĄ","‚Ėą‚Ėą‚Ėą‚Ėą‚Ėą‚Ėą ‚Ėą‚Ėą‚Ėą‚ĖĄ‚ĖÄ‚Ėą","‚Ėą‚Ėą‚Ėą‚Ėą ‚Ėą ‚Ėą‚Ėą‚Ė† ‚Ėą‚ĖĄ","‚ĖĄ‚ĖĄ‚ĖĄ‚ĖĄ‚ĖĄ‚ĖĄ ‚ĖĄ ‚ĖÄ‚ĖÄ‚ĖÄ‚ĖÄ","‚Ėą‚Ėą‚ĖĄ‚Ėą‚Ėą‚Ėą ‚Ėą‚Ėą‚Ėą‚Ėą‚Ėą‚Ėą","‚Ėą‚ĖÄ‚ĖĄ‚ĖÄ‚Ėą‚Ėą ‚Ėą‚ĖĄ‚ĖÄ‚ĖĄ‚Ėą‚Ėą","‚Ėą‚Ėą‚Ėą‚Ėą‚Ėą‚Ėą‚ĖĄ‚Ėą‚Ėą‚ĖÄ‚Ėą‚Ėą‚ĖÄ"],"colors":["011e01010101011e0119190909","01010101010107010101191919","010101011e01070101191e0119","02020202020207020701010101","02022c02020207020202020212","022c4c2c020207022c4c2c0202","0202020202020202022c020202"]},"E":{"chars":["‚ĖĄ    ‚Ėą‚ĖÄ‚Ėą‚Ėą‚Ėą‚Ė†‚ĖÄ‚Ėą"," ‚Ėą‚Ėą‚Ėą‚Ėą‚Ėą ‚ĖÄ‚ĖÄ‚ĖÄ‚ĖÄ‚ĖÄ‚ĖÄ","‚Ėą‚Ėą‚Ėą‚Ėą‚Ėą‚Ėą‚ĖĄ‚ĖĄ‚ĖĄ‚ĖĄ   ","‚ĖĄ‚ĖĄ‚ĖĄ ‚ĖÄ‚ĖÄ‚ĖÄ‚ĖÄ‚ĖÄ‚ĖÄ   ","‚Ėą‚Ėą‚Ėą‚Ėą‚ĖĄ‚Ėą ‚Ėą‚Ėą‚Ėą‚ĖÄ‚ĖĄ‚ĖÄ","‚Ėą‚Ėą‚Ėą‚ĖÄ‚ĖĄ‚ĖÄ ‚Ėą‚Ėą‚Ėą‚Ėą‚Ėą‚Ėą","‚ĖÄ‚Ėą‚Ėą‚Ėą‚Ėą‚Ėą‚ĖĄ‚Ėą‚Ėą‚Ėą‚Ėą‚Ėą‚ĖÄ"],"colors":["01191919190101010101191919","17010101010107010101010101","01010101010101010101070707","02020207010101010101070707","020202022c02070202022c4c2c","0202022c4c2c07020202020202","02020202020202020202020202"]},"F":{"chars":["‚Ėą‚Ėą‚Ėą‚Ėą‚Ėą‚Ėą‚ĖÄ‚Ėą‚Ėą‚Ė†‚ĖÄ‚ĖÄ‚Ėą","‚Ėą‚Ėą‚Ėą‚Ėą‚Ėą‚Ėą ‚Ėą‚Ėą‚Ėą‚ĖĄ‚ĖÄ‚ĖĄ","‚Ėą‚Ėą‚Ėą‚Ėą‚Ėą‚Ėą ‚Ėą‚Ėą‚Ė†‚Ėą‚Ėą‚Ėą","‚ĖÄ‚ĖÄ‚ĖÄ‚ĖÄ‚ĖÄ‚ĖÄ ‚ĖĄ‚ĖĄ‚ĖĄ‚ĖĄ‚ĖĄ‚ĖĄ","‚ĖĄ‚Ėą‚ĖĄ‚ĖÄ‚ĖÄ‚Ė† ‚ĖÄ‚ĖÄ‚ĖÄ‚ĖÄ‚ĖÄ‚ĖÄ","‚Ėą‚Ėą‚Ėą‚ĖĆ‚Ėą‚Ėą‚ĖĄ‚ĖĄ‚ĖĄ‚ĖĄ‚ĖÄ  ","‚Ėą‚Ėą‚Ėą‚Ėą‚Ėą‚ĖĄ       "],"colors":["01010101010101010119191919","01010101010107010101191919","01010101010107010119010101","01010101010107020202020202","28022828282807020202020202","28282828020202020202200707","28282828282807070707070707"]},"G":{"chars":["‚ĖĄ    ‚Ėą‚ĖÄ‚Ėą‚Ėą‚Ėą‚Ė†‚ĖÄ‚Ėą"," ‚Ėą‚Ėą‚Ėą‚Ėą‚Ėą ‚Ėą‚Ėą‚Ėą‚Ėą‚Ėą‚Ėą","‚Ėą‚Ėą‚Ėą‚Ėą‚Ėą‚Ėą ‚ĖÄ‚ĖÄ‚ĖÄ‚ĖÄ‚ĖÄ‚ĖÄ","‚ĖĄ‚ĖĄ‚ĖĄ ‚ĖÄ‚ĖÄ‚ĖÄ‚Ėą‚Ėą‚Ėą‚Ėą‚Ėą‚Ėą","‚Ėą‚Ėą‚Ėą‚Ėą‚ĖĄ‚Ėą ‚Ėą‚Ėą‚Ėą‚ĖÄ‚ĖĄ‚ĖÄ","‚Ėą‚Ėą‚Ėą‚ĖÄ‚ĖĄ‚ĖÄ ‚Ėą‚Ėą‚Ėą‚Ėą‚Ėą‚Ėą","‚ĖÄ‚Ėą‚Ėą‚Ėą‚Ėą‚Ėą‚ĖĄ‚Ėą‚Ėą‚Ėą‚Ėą‚Ėą‚Ėą"],"colors":["01191919190101010101191919","17010101010107010101010101","01010101010107010101010101","02020207010102020202020202","020202022c02070202022c4c2c","0202022c4c2c07020202020202","02020202020202020202020202"]},"H":{"chars":["‚Ėą ‚Ėą‚Ėą‚Ėą‚Ėą  ‚Ėą‚ĖÄ‚Ėą‚Ėą‚Ėą","‚Ėą‚Ėą‚Ėą‚Ėą‚Ėą‚Ėą ‚Ėą‚Ėą‚Ėą‚ĖĄ‚ĖÄ‚Ėą","‚Ėą‚Ėą‚Ėą‚Ėą ‚Ėą‚ĖĄ‚Ėą‚Ėą‚Ė† ‚Ėą‚ĖĄ","‚ĖĄ‚ĖĄ‚ĖĄ‚ĖĄ‚ĖĄ‚ĖĄ ‚ĖĄ ‚ĖÄ‚ĖÄ‚ĖÄ‚ĖÄ","‚Ėą‚Ėą‚ĖĄ‚Ėą‚Ėą‚Ėą ‚Ėą‚Ėą‚Ėą‚Ėą‚Ėą‚Ėą","‚Ėą‚ĖÄ‚ĖĄ‚ĖÄ‚Ėą‚Ėą ‚Ėą‚ĖĄ‚ĖÄ‚ĖĄ‚Ėą‚Ėą","‚Ėą‚Ėą‚Ėą‚Ėą‚Ėą‚Ėą ‚Ėą‚Ėą‚ĖÄ‚Ėą‚Ėą‚Ėą"],"colors":["011e01010101071e0119190909","01010101010107010101191919","010101011e01010101191e0119","02020202020207020701010101","02022c02020207020202020212","022c4c2c020207022c4c2c0202","0202020202020702022c020202"]},"I":{"chars":["‚ĖÄ‚ĖÄ‚ĖÄ‚ĖÄ‚ĖÄ‚ĖÄ","‚Ėą‚Ėą‚Ėą‚Ė†‚ĖÄ‚Ėą","‚Ėą‚Ėą‚Ėą‚Ėą‚Ė†‚Ėą","‚ĖĄ‚ĖĄ‚ĖĄ‚ĖĄ‚ĖĄ‚ĖĄ","‚ĖĄ‚ĖÄ‚ĖĄ‚Ėą‚Ėą‚Ėą","‚Ėą‚ĖÄ‚Ėą‚Ėą‚Ėą‚Ėą","‚Ėą‚Ėą‚Ėą‚Ėą‚Ėą‚Ėą"],"colors":["010101010109","010101191909","010101011901","020202020202","2c4c2c020202","022c02020202","020202020202"]},"J":{"chars":["       ‚Ėą‚Ėą‚ĖĄ‚ĖÄ‚ĖÄ‚Ėą","       ‚Ėą‚Ėą‚Ėą‚ĖĄ‚ĖÄ‚ĖĄ","‚Ėą‚Ėą‚Ėą‚Ėą‚Ėą‚Ėą ‚Ėą‚Ėą‚Ė†‚Ėą‚Ė†‚ĖÄ","‚ĖĄ‚ĖĄ‚ĖĄ‚ĖĄ ‚ĖÄ ‚ĖÄ‚ĖÄ‚ĖÄ‚ĖÄ‚ĖÄ‚ĖÄ","‚Ėą‚Ėą‚Ėą‚Ėą‚Ėą‚Ėą ‚Ėą‚ĖĄ‚ĖÄ‚ĖĄ‚Ėą‚Ėą","‚Ėą‚Ėą‚Ėą‚Ėą‚ĖĄ‚Ėą ‚Ėą‚Ėą‚ĖÄ‚Ėą‚Ėą‚Ėą","‚ĖÄ‚Ėą‚Ėą‚ĖÄ‚ĖĄ‚ĖÄ‚ĖĄ‚Ėą‚Ėą‚Ėą‚Ėą‚Ėą‚ĖÄ"],"colors":["07070707070707010119191909","07070707070707010101191919","01010101010107010119011919","02020202070107010101010101","02020202020207022c4c2c0202","020202022c020702022c020202","0202022c4c2c02020202020202"]},"K":{"chars":["‚Ėą ‚Ėą‚Ėą‚Ėą‚Ėą  ‚Ėą‚ĖÄ‚Ėą‚Ėą‚Ėą","‚Ėą‚Ėą‚Ėą‚Ėą‚Ėą‚Ėą ‚Ėą‚Ėą‚Ėą‚ĖĄ‚ĖÄ‚Ėą","‚Ėą‚Ėą‚Ėą‚Ėą ‚Ėą‚ĖĄ‚Ėą‚Ėą‚Ė† ‚Ėą ","‚ĖĄ‚ĖĄ‚ĖĄ‚ĖĄ‚ĖĄ‚ĖĄ ‚ĖĄ ‚ĖÄ‚ĖÄ  ","‚Ėą‚Ėą‚ĖĄ‚Ėą‚Ėą‚Ėą ‚Ėą‚Ėą‚Ėą‚Ėą‚Ėą‚ĖĄ","‚Ėą‚ĖÄ‚ĖĄ‚ĖÄ‚Ėą‚Ėą ‚Ėą‚ĖĄ‚ĖÄ‚ĖĄ‚Ėą‚Ėą","‚Ėą‚Ėą‚Ėą‚Ėą‚Ėą‚Ėą ‚Ėą‚Ėą‚ĖÄ‚Ėą‚Ėą‚Ėą"],"colors":["011e01010101071e0119190909","01010101010107010101191919","010101011e01010101191e0107","02020202020207020701010707","02022c02020207020202020202","022c4c2c020207022c4c2c0202","0202020202020702022c020202"]},"L":{"chars":["‚Ėą‚Ėą‚ĖĄ‚ĖÄ‚ĖÄ‚Ėą       ","‚Ėą‚Ėą‚Ėą‚ĖĄ‚ĖÄ‚ĖĄ       ","‚Ėą‚Ėą‚Ė†‚Ėą‚Ė†‚ĖÄ ‚Ėą‚Ėą‚Ėą‚Ėą‚Ėą‚Ėą","‚ĖÄ‚ĖÄ‚ĖÄ‚ĖÄ‚ĖÄ‚ĖÄ ‚ĖÄ ‚ĖĄ‚ĖĄ‚ĖĄ‚ĖĄ","‚Ėą‚Ėą‚ĖĄ‚ĖÄ‚ĖĄ‚Ėą ‚Ėą‚Ėą‚Ėą‚Ėą‚Ėą‚Ėą","‚Ėą‚Ėą‚Ėą‚ĖÄ‚Ėą‚Ėą ‚Ėą‚ĖĄ‚Ėą‚Ėą‚Ėą‚Ėą","‚ĖÄ‚Ėą‚Ėą‚Ėą‚Ėą‚Ėą‚ĖĄ‚ĖÄ‚ĖĄ‚ĖÄ‚Ėą‚Ėą‚ĖÄ"],"colors":["01011919190907070707070707","01010119191907070707070707","01011901191907010101010101","01010101010107010702020202","02022c4c2c0207020202020202","0202022c020207022c02020202","020202020202022c4c2c020202"]},"M":{"chars":["‚Ėą ‚Ėą‚Ėą‚Ėą‚Ėą‚ĖÄ ‚Ėą‚ĖÄ‚Ėą‚Ėą‚Ėą‚ĖÄ ‚Ėą‚ĖÄ‚Ėą‚Ėą‚ĖĄ","‚Ėą‚Ėą‚Ėą‚Ėą‚Ėą‚Ėą ‚Ėą‚Ėą‚Ėą‚ĖĄ‚ĖÄ‚Ėą ‚Ėą‚Ėą‚Ėą‚ĖĄ‚ĖÄ‚Ėą","‚Ėą‚Ėą‚Ėą‚Ėą ‚Ėą ‚Ėą‚Ėą‚Ė† ‚Ėą‚ĖĄ ‚Ėą‚Ėą‚Ė† ‚Ėą‚ĖĄ","‚ĖĄ‚ĖĄ‚ĖĄ‚ĖĄ‚ĖĄ‚ĖĄ ‚ĖĄ ‚ĖÄ‚ĖÄ‚ĖÄ‚ĖÄ ‚ĖĄ ‚ĖÄ‚ĖÄ‚ĖÄ‚ĖÄ","‚Ėą‚Ėą‚ĖĄ‚Ėą‚Ėą‚Ėą ‚Ėą‚Ėą‚Ėą‚Ėą‚Ėą‚Ėą ‚Ėą‚Ėą‚Ėą‚Ėą‚Ėą‚Ėą","‚Ėą‚ĖÄ‚ĖĄ‚ĖÄ‚Ėą‚Ėą ‚Ėą‚ĖĄ‚ĖÄ‚ĖĄ‚Ėą‚Ėą ‚Ėą‚ĖĄ‚ĖÄ‚ĖĄ‚Ėą‚Ėą","‚Ėą‚Ėą‚Ėą‚Ėą‚Ėą‚Ėą ‚Ėą‚Ėą‚ĖÄ‚Ėą‚Ėą‚Ėą ‚Ėą‚Ėą‚ĖÄ‚Ėą‚Ėą‚Ėą"],"colors":["011e01010101011e0119190909091e0119190909","0101010101010701010119191907010101191919","010101011e01070101191e0119070101191e0119","0202020202020702070101010107020701010101","02022c0202020702020202021207020202020212","022c4c2c020207022c4c2c020207022c4c2c0202","0202020202020702022c0202020702022c020202"]},"N":{"chars":["‚Ėą ‚Ėą‚Ėą‚Ėą‚Ėą‚ĖÄ ‚Ėą‚ĖÄ‚Ėą‚Ėą‚ĖĄ","‚Ėą‚Ėą‚Ėą‚Ėą‚Ėą‚Ėą ‚Ėą‚Ėą‚Ėą‚ĖĄ‚ĖÄ‚Ėą","‚Ėą‚Ėą‚Ėą‚Ėą ‚Ėą ‚Ėą‚Ėą‚Ė† ‚Ėą‚ĖĄ","‚ĖĄ‚ĖĄ‚ĖĄ‚ĖĄ‚ĖĄ‚ĖĄ ‚ĖĄ ‚ĖÄ‚ĖÄ‚ĖÄ‚ĖÄ","‚Ėą‚Ėą‚ĖĄ‚Ėą‚Ėą‚Ėą ‚Ėą‚Ėą‚Ėą‚Ėą‚Ėą‚Ėą","‚Ėą‚ĖÄ‚ĖĄ‚ĖÄ‚Ėą‚Ėą ‚Ėą‚ĖĄ‚ĖÄ‚ĖĄ‚Ėą‚Ėą","‚Ėą‚Ėą‚Ėą‚Ėą‚Ėą‚Ėą ‚Ėą‚Ėą‚ĖÄ‚Ėą‚Ėą‚Ėą"],"colors":["011e01010101011e0119190909","01010101010107010101191919","010101011e01070101191e0119","02020202020207020701010101","02022c02020207020202020212","022c4c2c020207022c4c2c0202","0202020202020702022c020202"]},"O":{"chars":["‚ĖĄ ‚Ėą‚Ėą‚Ėą‚Ėą‚ĖÄ ‚Ėą‚ĖÄ‚Ėą‚Ėą‚ĖĄ","‚Ėą‚Ėą‚Ėą‚Ėą‚Ėą‚Ėą ‚Ėą‚Ėą‚Ėą‚ĖĄ‚ĖÄ‚Ėą","‚Ėą‚Ėą‚Ėą‚Ėą ‚Ėą ‚Ėą‚Ėą‚Ė† ‚Ėą‚ĖĄ","‚ĖĄ‚ĖĄ‚ĖĄ‚ĖĄ‚ĖĄ‚ĖĄ ‚ĖĄ ‚ĖÄ‚ĖÄ‚ĖÄ‚ĖÄ","‚Ėą‚Ėą‚ĖĄ‚Ėą‚Ėą‚Ėą ‚Ėą‚Ėą‚Ėą‚Ėą‚Ėą‚Ėą","‚Ėą‚ĖÄ‚ĖĄ‚ĖÄ‚Ėą‚Ėą ‚Ėą‚ĖĄ‚ĖÄ‚ĖĄ‚Ėą‚Ėą","‚ĖÄ‚Ėą‚Ėą‚Ėą‚Ėą‚Ėą‚ĖĄ‚Ėą‚Ėą‚ĖÄ‚Ėą‚Ėą‚ĖÄ"],"colors":["011e01010101011e0119190909","01010101010107010101191919","010101011e01070101191e0119","02020202020207020701010101","02022c02020207020202020212","022c4c2c020207022c4c2c0202","0202020202020202022c020202"]},"P":{"chars":["‚Ėą ‚Ėą‚Ėą‚Ėą‚Ėą‚ĖÄ ‚Ėą‚ĖÄ‚Ėą‚Ėą‚ĖĄ","‚Ėą‚Ėą‚Ėą‚Ėą‚Ėą‚Ėą ‚Ėą‚Ėą‚Ėą‚ĖĄ‚ĖÄ‚Ėą","‚Ėą‚Ėą‚Ėą‚Ėą ‚Ėą‚ĖĄ‚Ėą‚Ėą‚Ė† ‚Ėą ","‚ĖĄ‚ĖĄ‚ĖĄ‚ĖĄ‚ĖĄ‚ĖĄ ‚ĖÄ‚ĖÄ‚ĖÄ‚ĖÄ  ","‚Ėą‚Ėą‚ĖĄ‚Ėą‚Ėą‚Ėą       ","‚Ėą‚ĖÄ‚ĖĄ‚ĖÄ‚Ėą‚Ėą       ","‚Ėą‚Ėą‚Ėą‚Ėą‚Ėą‚Ėą       "],"colors":["011e01010101011e0119190909","01010101010107010101191919","010101011e01010101191e0107","02020202020207010101010707","02022c02020207070707070707","022c4c2c020207070707070707","02020202020207070707070707"]},"Q":{"chars":["‚ĖĄ ‚Ėą‚Ėą‚Ėą‚Ėą‚ĖÄ ‚Ėą‚ĖÄ‚Ėą‚Ėą‚ĖĄ","‚Ėą‚Ėą‚Ėą‚Ėą‚Ėą‚Ėą ‚Ėą‚Ėą‚Ėą‚ĖĄ‚ĖÄ‚Ėą","‚Ėą‚Ėą‚Ėą‚Ėą ‚Ėą ‚Ėą‚Ėą‚Ė† ‚Ėą‚ĖĄ","‚ĖĄ‚ĖĄ‚ĖĄ‚ĖĄ‚ĖĄ‚ĖĄ ‚ĖĄ ‚ĖÄ‚ĖÄ‚ĖÄ‚ĖÄ","‚Ėą‚Ėą‚ĖĄ‚Ėą‚Ėą‚Ėą ‚Ėą‚Ėą‚Ėą‚Ėą‚Ėą‚Ėą","‚Ėą‚ĖÄ‚ĖĄ‚ĖÄ‚Ėą‚Ėą‚ĖĄ‚Ėą‚ĖĄ‚ĖÄ‚ĖĄ‚Ėą‚Ėą","‚ĖÄ‚Ėą‚Ėą‚Ėą‚Ėą‚Ėą‚ĖĄ‚Ėą‚Ėą‚ĖÄ‚Ėą‚Ėą‚ĖĄ"],"colors":["011e01010101011e0119190909","01010101010107010101191919","010101011e01070101191e0119","02020202020207020701010101","02022c02020207020202020212","022c4c2c020202022c4c2c0202","0202020202020202022c020202"]},"R":{"chars":["‚Ėą ‚Ėą‚Ėą‚Ėą‚Ėą‚ĖÄ ‚Ėą‚ĖÄ‚Ėą‚Ėą‚ĖĄ","‚Ėą‚Ėą‚Ėą‚Ėą‚Ėą‚Ėą ‚Ėą‚Ėą‚Ėą‚ĖĄ‚ĖÄ‚Ėą","‚Ėą‚Ėą‚Ėą‚Ėą ‚Ėą‚ĖĄ‚Ėą‚Ėą‚Ė† ‚Ėą ","‚ĖĄ‚ĖĄ‚ĖĄ‚ĖĄ‚ĖĄ‚ĖĄ ‚ĖĄ ‚ĖÄ‚ĖÄ  ","‚Ėą‚Ėą‚ĖĄ‚Ėą‚Ėą‚Ėą ‚Ėą‚Ėą‚Ėą‚Ėą‚Ėą‚ĖĄ","‚Ėą‚ĖÄ‚ĖĄ‚ĖÄ‚Ėą‚Ėą ‚Ėą‚ĖĄ‚ĖÄ‚ĖĄ‚Ėą‚Ėą","‚Ėą‚Ėą‚Ėą‚Ėą‚Ėą‚Ėą ‚Ėą‚Ėą‚ĖÄ‚Ėą‚Ėą‚Ėą"],"colors":["011e01010101011e0119190909","01010101010107010101191919","010101011e01010101191e0107","02020202020207020701010707","02022c02020207020202020202","022c4c2c020207022c4c2c0202","0202020202020702022c020202"]},"S":{"chars":["‚Ėą‚Ėą‚Ėą‚ĖÄ‚ĖÄ‚ĖÄ‚ĖÄ‚ĖÄ‚ĖÄ‚ĖÄ‚ĖÄ‚ĖÄ‚ĖÄ","‚ĖÄ‚ĖÄ‚ĖÄ‚ĖÄ‚ĖÄ‚ĖÄ‚ĖÄ ‚ĖĄ‚ĖÄ‚Ėź‚Ėą‚ĖĄ","‚Ėą‚Ėą‚Ėą‚Ėą‚Ėą‚Ėą  ‚Ė† ‚Ėą‚Ėą‚Ėą","‚ĖĄ‚ĖĄ‚ĖĄ‚ĖĄ‚ĖĄ‚ĖĄ ‚ĖĄ‚ĖĄ‚ĖĄ‚ĖĄ ‚ĖÄ","‚ĖĄ‚ĖÄ‚ĖĄ ‚Ėą‚Ėą ‚Ėą‚Ėą‚Ėą‚Ėą‚Ėą‚Ėą","‚Ėą‚ĖÄ   ‚Ėą ‚Ėą‚Ėą‚Ėą‚Ėą‚Ėą‚Ėą","‚ĖÄ‚Ėą‚Ėą‚Ėą‚Ėą‚Ėą‚ĖĄ‚Ėą‚ĖĄ‚ĖÄ‚ĖĄ‚Ėą‚ĖÄ"],"colors":["01010101010101010101010101","01010101010101191919191909","01010101010107191919010119","02020202020207020202020701","2c4c2c2c020207020202020202","022c2c2c2c0207020202020202","02020202020202022c4c2c0202"]},"T":{"chars":["‚Ėą‚Ėą‚Ėą‚Ėą‚ĖÄ‚Ėą‚Ėą‚Ėą‚Ėą‚Ėą‚Ėą‚ĖÄ‚Ėą‚ĖÄ‚ĖÄ‚Ėą","‚Ėą‚Ėą‚Ėą‚Ėą ‚Ėą‚Ėą‚Ėą‚Ėą‚Ėą‚Ėą ‚Ėą‚ĖĄ‚ĖÄ‚ĖĄ","     ‚Ėą‚Ėą‚Ėą‚Ėą‚Ėą‚Ėą     ","     ‚ĖÄ‚ĖÄ‚ĖÄ‚ĖÄ‚ĖÄ‚ĖÄ     ","     ‚ĖĄ‚Ėą‚ĖĄ‚ĖÄ‚ĖÄ‚Ė†     ","     ‚Ėą‚Ėą‚Ėą‚ĖĆ‚Ėą‚Ėą     ","     ‚Ėą‚Ėą‚Ėą‚Ėą‚Ėą‚ĖĄ     "],"colors":["01010101010101010101010101191919","01010101070101010101010701191919","07070707070101010101010707070707","07070707070101010101010707070707","07070707072802282828280707070707","07070707072828282802020707070707","07070707072828282828280707070707"]},"U":{"chars":["‚Ėą ‚Ėą‚Ėą‚Ėą‚Ėą  ‚Ėą‚ĖÄ‚Ėą‚Ėą‚Ėą","‚Ėą‚Ėą‚Ėą‚Ėą‚Ėą‚Ėą ‚Ėą‚Ėą‚Ėą‚ĖĄ‚ĖÄ‚Ėą","‚Ėą‚Ėą‚Ėą‚Ėą ‚Ėą ‚Ėą‚Ėą‚Ė† ‚Ėą‚ĖĄ","‚ĖĄ‚ĖĄ‚ĖĄ‚ĖĄ‚ĖĄ‚ĖĄ ‚ĖĄ ‚ĖÄ‚ĖÄ‚ĖÄ‚ĖÄ","‚Ėą‚Ėą‚ĖĄ‚Ėą‚Ėą‚Ėą ‚Ėą‚Ėą‚Ėą‚Ėą‚Ėą‚Ėą","‚Ėą‚ĖÄ‚ĖĄ‚ĖÄ‚Ėą‚Ėą ‚Ėą‚ĖĄ‚ĖÄ‚ĖĄ‚Ėą‚Ėą","‚ĖÄ‚Ėą‚Ėą‚Ėą‚Ėą‚Ėą‚ĖĄ‚Ėą‚Ėą‚ĖÄ‚Ėą‚Ėą‚ĖÄ"],"colors":["011e01010101071e0119190909","01010101010107010101191919","010101011e01070101191e0119","02020202020207020701010101","02022c02020207020202020212","022c4c2c020207022c4c2c0202","0202020202020202022c020202"]},"V":{"chars":["‚Ėą ‚Ėą‚Ėą‚Ėą‚Ėą  ‚Ėą‚ĖÄ‚Ėą‚Ėą‚Ėą","‚Ėą‚Ėą‚Ėą‚Ėą‚Ėą‚Ėą ‚Ėą‚Ėą‚Ėą‚ĖĄ‚ĖÄ‚Ėą","‚Ėą‚Ėą‚Ėą‚Ėą ‚Ėą ‚Ėą‚Ėą‚Ė† ‚Ėą‚ĖĄ","‚ĖĄ‚ĖĄ‚ĖĄ‚ĖĄ‚ĖĄ‚ĖĄ ‚ĖĄ ‚ĖÄ‚ĖÄ‚ĖÄ‚ĖÄ","‚Ėą‚Ėą‚ĖĄ‚Ėą‚Ėą‚Ėą ‚Ėą‚Ėą‚Ėą‚Ėą‚Ėą‚Ėą","‚Ėź‚ĖÄ‚ĖĄ‚ĖÄ‚Ėą‚Ėą ‚Ėą‚ĖĄ‚ĖÄ‚ĖĄ‚Ėą‚ĖĆ"," ‚ĖÄ‚Ėą‚Ėą‚Ėą‚Ėą‚ĖĄ‚Ėą‚Ėą‚ĖÄ‚Ėą‚ĖÄ "],"colors":["011e01010101071e0119190909","01010101010107010101191919","010101011e01070101191e0119","02020202020207020701010101","02022c02020207020202020212","022c4c2c020207022c4c2c0202","0702020202020202022c020207"]},"W":{"chars":["‚Ėą ‚Ėą‚Ėą‚Ėą‚Ėą  ‚Ėą‚ĖÄ‚Ėą‚Ėą‚Ėą  ‚Ėą‚ĖÄ‚Ėą‚Ėą‚Ėą","‚Ėą‚Ėą‚Ėą‚Ėą‚Ėą‚Ėą ‚Ėą‚Ėą‚Ėą‚ĖĄ‚ĖÄ‚Ėą ‚Ėą‚Ėą‚Ėą‚ĖĄ‚ĖÄ‚Ėą","‚Ėą‚Ėą‚Ėą‚Ėą ‚Ėą ‚Ėą‚Ėą‚Ė† ‚Ėą‚ĖĄ ‚Ėą‚Ėą‚Ė† ‚Ėą‚ĖĄ","‚ĖĄ‚ĖĄ‚ĖĄ‚ĖĄ‚ĖĄ‚ĖĄ ‚ĖĄ ‚ĖÄ‚ĖÄ‚ĖÄ‚ĖÄ ‚ĖĄ ‚ĖÄ‚ĖÄ‚ĖÄ‚ĖÄ","‚Ėą‚Ėą‚ĖĄ‚Ėą‚Ėą‚Ėą ‚Ėą‚Ėą‚Ėą‚Ėą‚Ėą‚Ėą ‚Ėą‚Ėą‚Ėą‚Ėą‚Ėą‚Ėą","‚Ėą‚ĖÄ‚ĖĄ‚ĖÄ‚Ėą‚Ėą ‚Ėą‚ĖĄ‚ĖÄ‚ĖĄ‚Ėą‚Ėą ‚Ėą‚ĖĄ‚ĖÄ‚ĖĄ‚Ėą‚Ėą","‚ĖÄ‚Ėą‚Ėą‚Ėą‚Ėą‚Ėą‚ĖĄ‚Ėą‚Ėą‚ĖÄ‚ĖÄ‚Ėą‚Ėą‚ĖĄ‚Ėą‚Ėą‚ĖÄ‚Ėą‚Ėą‚ĖÄ"],"colors":["011e01010101071e0119190909071e0119190909","0101010101010701010119191907010101191919","010101011e01070101191e0119070101191e0119","0202020202020702070101010107020701010101","02022c0202020702020202021207020202020212","022c4c2c020207022c4c2c020207022c4c2c0202","020202020202020202020202020202022c020202"]},"X":{"chars":["‚Ėą ‚Ėą‚Ėą‚Ėą‚Ėą  ‚Ėą‚ĖÄ‚Ėą‚Ėą‚Ėą","‚Ėź‚Ėą‚Ėą‚Ėą‚Ėą‚Ėą ‚Ėą‚Ėą‚Ėą‚ĖĄ‚ĖÄ‚Ėą"," ‚ĖÄ‚Ėą‚Ėą ‚Ėą‚ĖĄ‚Ėą‚Ėą‚Ė† ‚Ėą ","   ‚ĖĄ‚ĖĄ‚ĖĄ ‚ĖĄ ‚ĖÄ‚ĖÄ  ","‚ĖĄ‚Ėą‚ĖĄ‚Ėą‚Ėą‚Ėą ‚Ėą‚Ėą‚Ėą‚Ėą‚Ėą‚ĖĄ","‚Ėą‚ĖÄ‚ĖĄ‚ĖÄ‚Ėą‚Ėą ‚Ėą‚ĖĄ‚ĖÄ‚ĖĄ‚Ėą‚Ėą","‚Ėą‚Ėą‚Ėą‚Ėą‚Ėą‚Ėą ‚Ėą‚Ėą‚ĖÄ‚Ėą‚Ėą‚Ėą"],"colors":["011e01010101071e0119190909","01010101010107010101191919","070101011e01010101191e0107","07070702020207020701010707","02022c02020207020202020202","022c4c2c020207022c4c2c0202","0202020202020702022c020202"]},"Y":{"chars":["‚Ėą ‚Ėą‚Ėą‚Ėą‚Ėą  ‚Ėą‚ĖÄ‚Ėą‚Ėą‚Ėą","‚Ėą‚Ėą‚Ėą‚Ėą‚Ėą‚Ėą ‚Ėą‚Ėą‚Ėą‚ĖĄ‚ĖÄ‚Ėą","‚ĖÄ‚Ėą‚Ėą‚Ėą ‚Ėą‚ĖĄ‚Ėą‚Ėą‚Ė† ‚Ėą‚ĖĄ","       ‚ĖĄ ‚ĖÄ‚ĖÄ‚ĖÄ‚ĖÄ","‚Ėą‚Ėą‚ĖĄ‚Ėą‚Ėą‚Ėą ‚Ėą‚Ėą‚Ėą‚Ėą‚Ėą‚Ėą","‚Ėą‚ĖÄ‚ĖĄ‚ĖÄ‚Ėą‚Ėą ‚Ėą‚ĖĄ‚ĖÄ‚ĖĄ‚Ėą‚Ėą","‚Ėą‚Ėą‚Ėą‚Ėą‚Ėą‚Ėą‚ĖĄ‚Ėą‚Ėą‚ĖÄ‚Ėą‚Ėą‚ĖÄ"],"colors":["011e01010101071e0119190909","01010101010107010101191919","010101011e01010101191e0119","07070707070707020701010101","02022c02020207020202020212","022c4c2c020207022c4c2c0202","0202020202020202022c020202"]},"Z":{"chars":["‚ĖÄ‚ĖÄ‚ĖÄ‚ĖÄ‚ĖÄ‚ĖÄ‚ĖÄ‚ĖÄ‚ĖÄ‚ĖÄ‚Ė†‚ĖÄ‚Ėą","‚ĖĄ‚ĖĄ‚ĖÄ‚Ėź‚Ėą‚Ėą‚ĖÄ‚ĖÄ‚ĖÄ‚ĖÄ‚ĖÄ‚ĖÄ‚ĖÄ"," ‚Ė† ‚Ėą‚Ėą‚Ėą ‚Ėą‚Ėą‚Ėą‚Ėą‚Ėą‚Ėą","‚ĖÄ ‚ĖĄ‚ĖĄ‚ĖĄ‚ĖĄ ‚ĖĄ‚ĖĄ‚ĖĄ‚ĖĄ‚ĖĄ‚ĖĄ","‚Ėą‚Ėą‚Ėą‚Ėą‚Ėą‚Ėą ‚Ėą‚Ėą ‚ĖĄ‚ĖÄ‚ĖĄ","‚Ėą‚Ėą‚Ėą‚Ėą‚Ėą‚Ėą ‚Ėą   ‚ĖÄ‚Ėą","‚ĖÄ‚Ėą‚ĖĄ‚ĖÄ‚ĖĄ‚Ėą‚ĖĄ‚Ėą‚Ėą‚Ėą‚Ėą‚Ėą‚ĖÄ"],"colors":["01010101010101010101191909","01191919190909010901010101","19191901011907010101010101","01070202020207020202020202","0202020202020702022c2c4c2c","02020202020207022c2c2c2c02","02022c4c2c0202020202020202"]},"a":{"chars":["‚ĖĄ ‚Ėą‚Ėą‚Ėą‚Ėą‚ĖÄ ‚Ėą‚ĖÄ‚Ėą‚Ėą‚ĖĄ","‚Ėą‚Ėą‚Ėą‚Ėą‚Ėą‚Ėą ‚Ėą‚Ėą‚Ėą‚ĖĄ‚ĖÄ‚Ėą","‚Ėą‚Ėą‚Ėą‚Ėą ‚Ėą‚ĖĄ‚Ėą‚Ėą‚Ė† ‚Ėą‚ĖĄ","‚ĖĄ‚ĖĄ‚ĖĄ‚ĖĄ‚ĖĄ‚ĖĄ ‚ĖĄ ‚ĖÄ‚ĖÄ‚ĖÄ‚ĖÄ","‚Ėą‚Ėą‚ĖĄ‚Ėą‚Ėą‚Ėą ‚Ėą‚Ėą‚Ėą‚Ėą‚Ėą‚Ėą","‚Ėą‚ĖÄ‚ĖĄ‚ĖÄ‚Ėą‚Ėą ‚Ėą‚ĖĄ‚ĖÄ‚ĖĄ‚Ėą‚Ėą","‚Ėą‚Ėą‚Ėą‚Ėą‚Ėą‚Ėą ‚Ėą‚Ėą‚ĖÄ‚Ėą‚Ėą‚Ėą"],"colors":["011e01010101011e0119190909","01010101010107010101191919","010101011e01010101191e0119","02020202020207020701010101","02022c02020207020202020212","022c4c2c020207022c4c2c0202","0202020202020702022c020202"]},"b":{"chars":["‚Ėą ‚Ėą‚Ėą‚Ėą‚Ėą‚ĖÄ ‚Ėą‚ĖÄ‚Ėą‚Ėą‚ĖĄ","‚Ėą‚Ėą‚Ėą‚Ėą‚Ėą‚Ėą ‚Ėą‚Ėą‚Ėą‚ĖĄ‚ĖÄ‚ĖÄ","‚Ėą‚Ėą‚Ėą‚Ėą ‚Ėą‚ĖĄ‚Ėą‚Ėą‚Ė† ‚ĖĄ ","‚ĖĄ‚ĖĄ‚ĖĄ‚ĖĄ‚ĖĄ‚ĖĄ ‚ĖĄ ‚ĖÄ‚ĖÄ‚ĖÄ‚ĖÄ","‚Ėą‚Ėą‚ĖĄ‚Ėą‚Ėą‚Ėą ‚Ėą‚Ėą‚Ėą‚Ėą‚Ėą‚Ėą","‚Ėą‚ĖÄ‚ĖĄ‚ĖÄ‚Ėą‚Ėą ‚Ėą‚ĖĄ‚ĖÄ‚ĖĄ‚Ėą‚Ėą","‚Ėą‚Ėą‚Ėą‚Ėą‚Ėą‚Ėą‚ĖĄ‚Ėą‚Ėą‚ĖÄ‚Ėą‚Ėą‚ĖÄ"],"colors":["011e01010101011e0119190909","01010101010107010101191901","010101011e01010101191e0107","02020202020207020701010101","02022c02020207020202020212","022c4c2c020207022c4c2c0202","0202020202020202022c020202"]},"c":{"chars":["‚ĖĄ    ‚Ėą‚ĖÄ‚Ėą‚Ėą‚Ėą‚Ė†‚ĖÄ‚Ėą"," ‚Ėą‚Ėą‚Ėą‚Ėą‚Ėą ‚Ėą‚Ėą‚Ėą‚Ėą‚Ėą‚Ėą","‚Ėą‚Ėą‚Ėą‚Ėą‚Ėą‚Ėą ‚ĖÄ‚ĖÄ‚ĖÄ‚ĖÄ‚ĖÄ‚ĖÄ","‚ĖĄ‚ĖĄ‚ĖĄ ‚ĖÄ‚ĖÄ       ","‚Ėą‚Ėą‚Ėą‚Ėą‚ĖĄ‚Ėą ‚Ėą‚Ėą‚Ėą‚ĖÄ‚ĖĄ‚ĖÄ","‚Ėą‚Ėą‚Ėą‚ĖÄ‚ĖĄ‚ĖÄ ‚Ėą‚Ėą‚Ėą‚Ėą‚Ėą‚Ėą","‚ĖÄ‚Ėą‚Ėą‚Ėą‚Ėą‚Ėą‚ĖĄ‚Ėą‚Ėą‚Ėą‚Ėą‚Ėą‚ĖÄ"],"colors":["01191919190101010101191919","17010101010107010101010101","01010101010107010101010101","02020207010107070707070707","020202022c02070202022c4c2c","0202022c4c2c07020202020202","02020202020202020202020202"]},"d":{"chars":["‚Ėą ‚Ėą‚Ėą‚Ėą‚Ėą‚ĖÄ ‚Ėą‚ĖÄ‚Ėą‚Ėą‚ĖĄ","‚Ėą‚Ėą‚Ėą‚Ėą‚Ėą‚Ėą ‚Ėą‚Ėą‚Ėą‚ĖĄ‚ĖÄ‚Ėą","‚Ėą‚Ėą‚Ėą‚Ėą ‚Ėą ‚Ėą‚Ėą‚Ė† ‚Ėą‚ĖĄ","‚ĖĄ‚ĖĄ‚ĖĄ‚ĖĄ‚ĖĄ‚ĖĄ ‚ĖĄ ‚ĖÄ‚ĖÄ‚ĖÄ‚ĖÄ","‚Ėą‚Ėą‚ĖĄ‚Ėą‚Ėą‚Ėą ‚Ėą‚Ėą‚Ėą‚Ėą‚Ėą‚Ėą","‚Ėą‚ĖÄ‚ĖĄ‚ĖÄ‚Ėą‚Ėą ‚Ėą‚ĖĄ‚ĖÄ‚ĖĄ‚Ėą‚Ėą","‚Ėą‚Ėą‚Ėą‚Ėą‚Ėą‚Ėą‚ĖĄ‚Ėą‚Ėą‚ĖÄ‚Ėą‚Ėą‚ĖÄ"],"colors":["011e01010101011e0119190909","01010101010107010101191919","010101011e01070101191e0119","02020202020207020701010101","02022c02020207020202020212","022c4c2c020207022c4c2c0202","0202020202020202022c020202"]},"e":{"chars":["‚ĖĄ    ‚Ėą‚ĖÄ‚Ėą‚Ėą‚Ėą‚Ė†‚ĖÄ‚Ėą"," ‚Ėą‚Ėą‚Ėą‚Ėą‚Ėą ‚ĖÄ‚ĖÄ‚ĖÄ‚ĖÄ‚ĖÄ‚ĖÄ","‚Ėą‚Ėą‚Ėą‚Ėą‚Ėą‚Ėą‚ĖĄ‚ĖĄ‚ĖĄ‚ĖĄ   ","‚ĖĄ‚ĖĄ‚ĖĄ ‚ĖÄ‚ĖÄ‚ĖÄ‚ĖÄ‚ĖÄ‚ĖÄ   ","‚Ėą‚Ėą‚Ėą‚Ėą‚ĖĄ‚Ėą ‚Ėą‚Ėą‚Ėą‚ĖÄ‚ĖĄ‚ĖÄ","‚Ėą‚Ėą‚Ėą‚ĖÄ‚ĖĄ‚ĖÄ ‚Ėą‚Ėą‚Ėą‚Ėą‚Ėą‚Ėą","‚ĖÄ‚Ėą‚Ėą‚Ėą‚Ėą‚Ėą‚ĖĄ‚Ėą‚Ėą‚Ėą‚Ėą‚Ėą‚ĖÄ"],"colors":["01191919190101010101191919","17010101010107010101010101","01010101010101010101070707","02020207010101010101070707","020202022c02070202022c4c2c","0202022c4c2c07020202020202","02020202020202020202020202"]},"f":{"chars":["‚Ėą‚Ėą‚Ėą‚Ėą‚Ėą‚Ėą‚ĖÄ‚Ėą‚Ėą‚Ė†‚ĖÄ‚ĖÄ‚Ėą","‚Ėą‚Ėą‚Ėą‚Ėą‚Ėą‚Ėą ‚Ėą‚Ėą‚Ėą‚ĖĄ‚ĖÄ‚ĖĄ","‚Ėą‚Ėą‚Ėą‚Ėą‚Ėą‚Ėą ‚Ėą‚Ėą‚Ė†‚Ėą‚Ėą‚Ėą","‚ĖÄ‚ĖÄ‚ĖÄ‚ĖÄ‚ĖÄ‚ĖÄ ‚ĖĄ‚ĖĄ‚ĖĄ‚ĖĄ‚ĖĄ‚ĖĄ","‚ĖĄ‚Ėą‚ĖĄ‚ĖÄ‚ĖÄ‚Ė† ‚ĖÄ‚ĖÄ‚ĖÄ‚ĖÄ‚ĖÄ‚ĖÄ","‚Ėą‚Ėą‚Ėą‚ĖĆ‚Ėą‚Ėą‚ĖĄ‚ĖĄ‚ĖĄ‚ĖĄ‚ĖÄ  ","‚Ėą‚Ėą‚Ėą‚Ėą‚Ėą‚ĖĄ       "],"colors":["01010101010101010119191919","01010101010107010101191919","01010101010107010119010101","01010101010107020202020202","28022828282807020202020202","28282828020202020202200707","28282828282807070707070707"]},"g":{"chars":["‚ĖĄ    ‚Ėą‚ĖÄ‚Ėą‚Ėą‚Ėą‚Ė†‚ĖÄ‚Ėą"," ‚Ėą‚Ėą‚Ėą‚Ėą‚Ėą ‚Ėą‚Ėą‚Ėą‚Ėą‚Ėą‚Ėą","‚Ėą‚Ėą‚Ėą‚Ėą‚Ėą‚Ėą ‚ĖÄ‚ĖÄ‚ĖÄ‚ĖÄ‚ĖÄ‚ĖÄ","‚ĖĄ‚ĖĄ‚ĖĄ ‚ĖÄ‚ĖÄ‚ĖÄ‚Ėą‚Ėą‚Ėą‚Ėą‚Ėą‚Ėą","‚Ėą‚Ėą‚Ėą‚Ėą‚ĖĄ‚Ėą ‚Ėą‚Ėą‚Ėą‚ĖÄ‚ĖĄ‚ĖÄ","‚Ėą‚Ėą‚Ėą‚ĖÄ‚ĖĄ‚ĖÄ ‚Ėą‚Ėą‚Ėą‚Ėą‚Ėą‚Ėą","‚ĖÄ‚Ėą‚Ėą‚Ėą‚Ėą‚Ėą‚ĖĄ‚Ėą‚Ėą‚Ėą‚Ėą‚Ėą‚Ėą"],"colors":["01191919190101010101191919","17010101010107010101010101","01010101010107010101010101","02020207010102020202020202","020202022c02070202022c4c2c","0202022c4c2c07020202020202","02020202020202020202020202"]},"h":{"chars":["‚Ėą ‚Ėą‚Ėą‚Ėą‚Ėą  ‚Ėą‚ĖÄ‚Ėą‚Ėą‚Ėą","‚Ėą‚Ėą‚Ėą‚Ėą‚Ėą‚Ėą ‚Ėą‚Ėą‚Ėą‚ĖĄ‚ĖÄ‚Ėą","‚Ėą‚Ėą‚Ėą‚Ėą ‚Ėą‚ĖĄ‚Ėą‚Ėą‚Ė† ‚Ėą‚ĖĄ","‚ĖĄ‚ĖĄ‚ĖĄ‚ĖĄ‚ĖĄ‚ĖĄ ‚ĖĄ ‚ĖÄ‚ĖÄ‚ĖÄ‚ĖÄ","‚Ėą‚Ėą‚ĖĄ‚Ėą‚Ėą‚Ėą ‚Ėą‚Ėą‚Ėą‚Ėą‚Ėą‚Ėą","‚Ėą‚ĖÄ‚ĖĄ‚ĖÄ‚Ėą‚Ėą ‚Ėą‚ĖĄ‚ĖÄ‚ĖĄ‚Ėą‚Ėą","‚Ėą‚Ėą‚Ėą‚Ėą‚Ėą‚Ėą ‚Ėą‚Ėą‚ĖÄ‚Ėą‚Ėą‚Ėą"],"colors":["011e01010101071e0119190909","01010101010107010101191919","010101011e01010101191e0119","02020202020207020701010101","02022c02020207020202020212","022c4c2c020207022c4c2c0202","0202020202020702022c020202"]},"i":{"chars":["‚ĖÄ‚ĖÄ‚ĖÄ‚ĖÄ‚ĖÄ‚ĖÄ","‚Ėą‚Ėą‚Ėą‚Ė†‚ĖÄ‚Ėą","‚Ėą‚Ėą‚Ėą‚Ėą‚Ė†‚Ėą","‚ĖĄ‚ĖĄ‚ĖĄ‚ĖĄ‚ĖĄ‚ĖĄ","‚ĖĄ‚ĖÄ‚ĖĄ‚Ėą‚Ėą‚Ėą","‚Ėą‚ĖÄ‚Ėą‚Ėą‚Ėą‚Ėą","‚Ėą‚Ėą‚Ėą‚Ėą‚Ėą‚Ėą"],"colors":["010101010109","010101191909","010101011901","020202020202","2c4c2c020202","022c02020202","020202020202"]},"j":{"chars":["       ‚Ėą‚Ėą‚ĖĄ‚ĖÄ‚ĖÄ‚Ėą","       ‚Ėą‚Ėą‚Ėą‚ĖĄ‚ĖÄ‚ĖĄ","‚Ėą‚Ėą‚Ėą‚Ėą‚Ėą‚Ėą ‚Ėą‚Ėą‚Ė†‚Ėą‚Ė†‚ĖÄ","‚ĖĄ‚ĖĄ‚ĖĄ‚ĖĄ ‚ĖÄ ‚ĖÄ‚ĖÄ‚ĖÄ‚ĖÄ‚ĖÄ‚ĖÄ","‚Ėą‚Ėą‚Ėą‚Ėą‚Ėą‚Ėą ‚Ėą‚ĖĄ‚ĖÄ‚ĖĄ‚Ėą‚Ėą","‚Ėą‚Ėą‚Ėą‚Ėą‚ĖĄ‚Ėą ‚Ėą‚Ėą‚ĖÄ‚Ėą‚Ėą‚Ėą","‚ĖÄ‚Ėą‚Ėą‚ĖÄ‚ĖĄ‚ĖÄ‚ĖĄ‚Ėą‚Ėą‚Ėą‚Ėą‚Ėą‚ĖÄ"],"colors":["07070707070707010119191909","07070707070707010101191919","01010101010107010119011919","02020202070107010101010101","02020202020207022c4c2c0202","020202022c020702022c020202","0202022c4c2c02020202020202"]},"k":{"chars":["‚Ėą ‚Ėą‚Ėą‚Ėą‚Ėą  ‚Ėą‚ĖÄ‚Ėą‚Ėą‚Ėą","‚Ėą‚Ėą‚Ėą‚Ėą‚Ėą‚Ėą ‚Ėą‚Ėą‚Ėą‚ĖĄ‚ĖÄ‚Ėą","‚Ėą‚Ėą‚Ėą‚Ėą ‚Ėą‚ĖĄ‚Ėą‚Ėą‚Ė† ‚Ėą ","‚ĖĄ‚ĖĄ‚ĖĄ‚ĖĄ‚ĖĄ‚ĖĄ ‚ĖĄ ‚ĖÄ‚ĖÄ  ","‚Ėą‚Ėą‚ĖĄ‚Ėą‚Ėą‚Ėą ‚Ėą‚Ėą‚Ėą‚Ėą‚Ėą‚ĖĄ","‚Ėą‚ĖÄ‚ĖĄ‚ĖÄ‚Ėą‚Ėą ‚Ėą‚ĖĄ‚ĖÄ‚ĖĄ‚Ėą‚Ėą","‚Ėą‚Ėą‚Ėą‚Ėą‚Ėą‚Ėą ‚Ėą‚Ėą‚ĖÄ‚Ėą‚Ėą‚Ėą"],"colors":["011e01010101071e0119190909","01010101010107010101191919","010101011e01010101191e0107","02020202020207020701010707","02022c02020207020202020202","022c4c2c020207022c4c2c0202","0202020202020702022c020202"]},"l":{"chars":["‚Ėą‚Ėą‚ĖĄ‚ĖÄ‚ĖÄ‚Ėą       ","‚Ėą‚Ėą‚Ėą‚ĖĄ‚ĖÄ‚ĖĄ       ","‚Ėą‚Ėą‚Ė†‚Ėą‚Ė†‚ĖÄ ‚Ėą‚Ėą‚Ėą‚Ėą‚Ėą‚Ėą","‚ĖÄ‚ĖÄ‚ĖÄ‚ĖÄ‚ĖÄ‚ĖÄ ‚ĖÄ ‚ĖĄ‚ĖĄ‚ĖĄ‚ĖĄ","‚Ėą‚Ėą‚ĖĄ‚ĖÄ‚ĖĄ‚Ėą ‚Ėą‚Ėą‚Ėą‚Ėą‚Ėą‚Ėą","‚Ėą‚Ėą‚Ėą‚ĖÄ‚Ėą‚Ėą ‚Ėą‚ĖĄ‚Ėą‚Ėą‚Ėą‚Ėą","‚ĖÄ‚Ėą‚Ėą‚Ėą‚Ėą‚Ėą‚ĖĄ‚ĖÄ‚ĖĄ‚ĖÄ‚Ėą‚Ėą‚ĖÄ"],"colors":["01011919190907070707070707","01010119191907070707070707","01011901191907010101010101","01010101010107010702020202","02022c4c2c0207020202020202","0202022c020207022c02020202","020202020202022c4c2c020202"]},"m":{"chars":["‚Ėą ‚Ėą‚Ėą‚Ėą‚Ėą‚ĖÄ ‚Ėą‚ĖÄ‚Ėą‚Ėą‚Ėą‚ĖÄ ‚Ėą‚ĖÄ‚Ėą‚Ėą‚ĖĄ","‚Ėą‚Ėą‚Ėą‚Ėą‚Ėą‚Ėą ‚Ėą‚Ėą‚Ėą‚ĖĄ‚ĖÄ‚Ėą ‚Ėą‚Ėą‚Ėą‚ĖĄ‚ĖÄ‚Ėą","‚Ėą‚Ėą‚Ėą‚Ėą ‚Ėą ‚Ėą‚Ėą‚Ė† ‚Ėą‚ĖĄ ‚Ėą‚Ėą‚Ė† ‚Ėą‚ĖĄ","‚ĖĄ‚ĖĄ‚ĖĄ‚ĖĄ‚ĖĄ‚ĖĄ ‚ĖĄ ‚ĖÄ‚ĖÄ‚ĖÄ‚ĖÄ ‚ĖĄ ‚ĖÄ‚ĖÄ‚ĖÄ‚ĖÄ","‚Ėą‚Ėą‚ĖĄ‚Ėą‚Ėą‚Ėą ‚Ėą‚Ėą‚Ėą‚Ėą‚Ėą‚Ėą ‚Ėą‚Ėą‚Ėą‚Ėą‚Ėą‚Ėą","‚Ėą‚ĖÄ‚ĖĄ‚ĖÄ‚Ėą‚Ėą ‚Ėą‚ĖĄ‚ĖÄ‚ĖĄ‚Ėą‚Ėą ‚Ėą‚ĖĄ‚ĖÄ‚ĖĄ‚Ėą‚Ėą","‚Ėą‚Ėą‚Ėą‚Ėą‚Ėą‚Ėą ‚Ėą‚Ėą‚ĖÄ‚Ėą‚Ėą‚Ėą ‚Ėą‚Ėą‚ĖÄ‚Ėą‚Ėą‚Ėą"],"colors":["011e01010101011e0119190909091e0119190909","0101010101010701010119191907010101191919","010101011e01070101191e0119070101191e0119","0202020202020702070101010107020701010101","02022c0202020702020202021207020202020212","022c4c2c020207022c4c2c020207022c4c2c0202","0202020202020702022c0202020702022c020202"]},"n":{"chars":["‚Ėą ‚Ėą‚Ėą‚Ėą‚Ėą‚ĖÄ ‚Ėą‚ĖÄ‚Ėą‚Ėą‚ĖĄ","‚Ėą‚Ėą‚Ėą‚Ėą‚Ėą‚Ėą ‚Ėą‚Ėą‚Ėą‚ĖĄ‚ĖÄ‚Ėą","‚Ėą‚Ėą‚Ėą‚Ėą ‚Ėą ‚Ėą‚Ėą‚Ė† ‚Ėą‚ĖĄ","‚ĖĄ‚ĖĄ‚ĖĄ‚ĖĄ‚ĖĄ‚ĖĄ ‚ĖĄ ‚ĖÄ‚ĖÄ‚ĖÄ‚ĖÄ","‚Ėą‚Ėą‚ĖĄ‚Ėą‚Ėą‚Ėą ‚Ėą‚Ėą‚Ėą‚Ėą‚Ėą‚Ėą","‚Ėą‚ĖÄ‚ĖĄ‚ĖÄ‚Ėą‚Ėą ‚Ėą‚ĖĄ‚ĖÄ‚ĖĄ‚Ėą‚Ėą","‚Ėą‚Ėą‚Ėą‚Ėą‚Ėą‚Ėą ‚Ėą‚Ėą‚ĖÄ‚Ėą‚Ėą‚Ėą"],"colors":["011e01010101011e0119190909","01010101010107010101191919","010101011e01070101191e0119","02020202020207020701010101","02022c02020207020202020212","022c4c2c020207022c4c2c0202","0202020202020702022c020202"]},"o":{"chars":["‚ĖĄ ‚Ėą‚Ėą‚Ėą‚Ėą‚ĖÄ ‚Ėą‚ĖÄ‚Ėą‚Ėą‚ĖĄ","‚Ėą‚Ėą‚Ėą‚Ėą‚Ėą‚Ėą ‚Ėą‚Ėą‚Ėą‚ĖĄ‚ĖÄ‚Ėą","‚Ėą‚Ėą‚Ėą‚Ėą ‚Ėą ‚Ėą‚Ėą‚Ė† ‚Ėą‚ĖĄ","‚ĖĄ‚ĖĄ‚ĖĄ‚ĖĄ‚ĖĄ‚ĖĄ ‚ĖĄ ‚ĖÄ‚ĖÄ‚ĖÄ‚ĖÄ","‚Ėą‚Ėą‚ĖĄ‚Ėą‚Ėą‚Ėą ‚Ėą‚Ėą‚Ėą‚Ėą‚Ėą‚Ėą","‚Ėą‚ĖÄ‚ĖĄ‚ĖÄ‚Ėą‚Ėą ‚Ėą‚ĖĄ‚ĖÄ‚ĖĄ‚Ėą‚Ėą","‚ĖÄ‚Ėą‚Ėą‚Ėą‚Ėą‚Ėą‚ĖĄ‚Ėą‚Ėą‚ĖÄ‚Ėą‚Ėą‚ĖÄ"],"colors":["011e01010101011e0119190909","01010101010107010101191919","010101011e01070101191e0119","02020202020207020701010101","02022c02020207020202020212","022c4c2c020207022c4c2c0202","0202020202020202022c020202"]},"p":{"chars":["‚Ėą ‚Ėą‚Ėą‚Ėą‚Ėą‚ĖÄ ‚Ėą‚ĖÄ‚Ėą‚Ėą‚ĖĄ","‚Ėą‚Ėą‚Ėą‚Ėą‚Ėą‚Ėą ‚Ėą‚Ėą‚Ėą‚ĖĄ‚ĖÄ‚Ėą","‚Ėą‚Ėą‚Ėą‚Ėą ‚Ėą‚ĖĄ‚Ėą‚Ėą‚Ė† ‚Ėą ","‚ĖĄ‚ĖĄ‚ĖĄ‚ĖĄ‚ĖĄ‚ĖĄ ‚ĖÄ‚ĖÄ‚ĖÄ‚ĖÄ  ","‚Ėą‚Ėą‚ĖĄ‚Ėą‚Ėą‚Ėą       ","‚Ėą‚ĖÄ‚ĖĄ‚ĖÄ‚Ėą‚Ėą       ","‚Ėą‚Ėą‚Ėą‚Ėą‚Ėą‚Ėą       "],"colors":["011e01010101011e0119190909","01010101010107010101191919","010101011e01010101191e0107","02020202020207010101010707","02022c02020207070707070707","022c4c2c020207070707070707","02020202020207070707070707"]},"q":{"chars":["‚ĖĄ ‚Ėą‚Ėą‚Ėą‚Ėą‚ĖÄ ‚Ėą‚ĖÄ‚Ėą‚Ėą‚ĖĄ","‚Ėą‚Ėą‚Ėą‚Ėą‚Ėą‚Ėą ‚Ėą‚Ėą‚Ėą‚ĖĄ‚ĖÄ‚Ėą","‚Ėą‚Ėą‚Ėą‚Ėą ‚Ėą ‚Ėą‚Ėą‚Ė† ‚Ėą‚ĖĄ","‚ĖĄ‚ĖĄ‚ĖĄ‚ĖĄ‚ĖĄ‚ĖĄ ‚ĖĄ ‚ĖÄ‚ĖÄ‚ĖÄ‚ĖÄ","‚Ėą‚Ėą‚ĖĄ‚Ėą‚Ėą‚Ėą ‚Ėą‚Ėą‚Ėą‚Ėą‚Ėą‚Ėą","‚Ėą‚ĖÄ‚ĖĄ‚ĖÄ‚Ėą‚Ėą‚ĖĄ‚Ėą‚ĖĄ‚ĖÄ‚ĖĄ‚Ėą‚Ėą","‚ĖÄ‚Ėą‚Ėą‚Ėą‚Ėą‚Ėą‚ĖĄ‚Ėą‚Ėą‚ĖÄ‚Ėą‚Ėą‚ĖĄ"],"colors":["011e01010101011e0119190909","01010101010107010101191919","010101011e01070101191e0119","02020202020207020701010101","02022c02020207020202020212","022c4c2c020202022c4c2c0202","0202020202020202022c020202"]},"r":{"chars":["‚Ėą ‚Ėą‚Ėą‚Ėą‚Ėą‚ĖÄ ‚Ėą‚ĖÄ‚Ėą‚Ėą‚ĖĄ","‚Ėą‚Ėą‚Ėą‚Ėą‚Ėą‚Ėą ‚Ėą‚Ėą‚Ėą‚ĖĄ‚ĖÄ‚Ėą","‚Ėą‚Ėą‚Ėą‚Ėą ‚Ėą‚ĖĄ‚Ėą‚Ėą‚Ė† ‚Ėą ","‚ĖĄ‚ĖĄ‚ĖĄ‚ĖĄ‚ĖĄ‚ĖĄ ‚ĖĄ ‚ĖÄ‚ĖÄ  ","‚Ėą‚Ėą‚ĖĄ‚Ėą‚Ėą‚Ėą ‚Ėą‚Ėą‚Ėą‚Ėą‚Ėą‚ĖĄ","‚Ėą‚ĖÄ‚ĖĄ‚ĖÄ‚Ėą‚Ėą ‚Ėą‚ĖĄ‚ĖÄ‚ĖĄ‚Ėą‚Ėą","‚Ėą‚Ėą‚Ėą‚Ėą‚Ėą‚Ėą ‚Ėą‚Ėą‚ĖÄ‚Ėą‚Ėą‚Ėą"],"colors":["011e01010101011e0119190909","01010101010107010101191919","010101011e01010101191e0107","02020202020207020701010707","02022c02020207020202020202","022c4c2c020207022c4c2c0202","0202020202020702022c020202"]},"s":{"chars":["‚Ėą‚Ėą‚Ėą‚ĖÄ‚ĖÄ‚ĖÄ‚ĖÄ‚ĖÄ‚ĖÄ‚ĖÄ‚ĖÄ‚ĖÄ‚ĖÄ","‚ĖÄ‚ĖÄ‚ĖÄ‚ĖÄ‚ĖÄ‚ĖÄ‚ĖÄ ‚ĖĄ‚ĖÄ‚Ėź‚Ėą‚ĖĄ","‚Ėą‚Ėą‚Ėą‚Ėą‚Ėą‚Ėą  ‚Ė† ‚Ėą‚Ėą‚Ėą","‚ĖĄ‚ĖĄ‚ĖĄ‚ĖĄ‚ĖĄ‚ĖĄ ‚ĖĄ‚ĖĄ‚ĖĄ‚ĖĄ ‚ĖÄ","‚ĖĄ‚ĖÄ‚ĖĄ ‚Ėą‚Ėą ‚Ėą‚Ėą‚Ėą‚Ėą‚Ėą‚Ėą","‚Ėą‚ĖÄ   ‚Ėą ‚Ėą‚Ėą‚Ėą‚Ėą‚Ėą‚Ėą","‚ĖÄ‚Ėą‚Ėą‚Ėą‚Ėą‚Ėą‚ĖĄ‚Ėą‚ĖĄ‚ĖÄ‚ĖĄ‚Ėą‚ĖÄ"],"colors":["01010101010101010101010101","01010101010101191919191909","01010101010107191919010119","02020202020207020202020701","2c4c2c2c020207020202020202","022c2c2c2c0207020202020202","02020202020202022c4c2c0202"]},"t":{"chars":["‚Ėą‚Ėą‚Ėą‚Ėą‚ĖÄ‚Ėą‚Ėą‚Ėą‚Ėą‚Ėą‚Ėą‚ĖÄ‚Ėą‚ĖÄ‚ĖÄ‚Ėą","‚Ėą‚Ėą‚Ėą‚Ėą ‚Ėą‚Ėą‚Ėą‚Ėą‚Ėą‚Ėą ‚Ėą‚ĖĄ‚ĖÄ‚ĖĄ","     ‚Ėą‚Ėą‚Ėą‚Ėą‚Ėą‚Ėą     ","     ‚ĖÄ‚ĖÄ‚ĖÄ‚ĖÄ‚ĖÄ‚ĖÄ     ","     ‚ĖĄ‚Ėą‚ĖĄ‚ĖÄ‚ĖÄ‚Ė†     ","     ‚Ėą‚Ėą‚Ėą‚ĖĆ‚Ėą‚Ėą     ","     ‚Ėą‚Ėą‚Ėą‚Ėą‚Ėą‚ĖĄ     "],"colors":["01010101010101010101010101191919","01010101070101010101010701191919","07070707070101010101010707070707","07070707070101010101010707070707","07070707072802282828280707070707","07070707072828282802020707070707","07070707072828282828280707070707"]},"u":{"chars":["‚Ėą ‚Ėą‚Ėą‚Ėą‚Ėą  ‚Ėą‚ĖÄ‚Ėą‚Ėą‚Ėą","‚Ėą‚Ėą‚Ėą‚Ėą‚Ėą‚Ėą ‚Ėą‚Ėą‚Ėą‚ĖĄ‚ĖÄ‚Ėą","‚Ėą‚Ėą‚Ėą‚Ėą ‚Ėą ‚Ėą‚Ėą‚Ė† ‚Ėą‚ĖĄ","‚ĖĄ‚ĖĄ‚ĖĄ‚ĖĄ‚ĖĄ‚ĖĄ ‚ĖĄ ‚ĖÄ‚ĖÄ‚ĖÄ‚ĖÄ","‚Ėą‚Ėą‚ĖĄ‚Ėą‚Ėą‚Ėą ‚Ėą‚Ėą‚Ėą‚Ėą‚Ėą‚Ėą","‚Ėą‚ĖÄ‚ĖĄ‚ĖÄ‚Ėą‚Ėą ‚Ėą‚ĖĄ‚ĖÄ‚ĖĄ‚Ėą‚Ėą","‚ĖÄ‚Ėą‚Ėą‚Ėą‚Ėą‚Ėą‚ĖĄ‚Ėą‚Ėą‚ĖÄ‚Ėą‚Ėą‚ĖÄ"],"colors":["011e01010101071e0119190909","01010101010107010101191919","010101011e01070101191e0119","02020202020207020701010101","02022c02020207020202020212","022c4c2c020207022c4c2c0202","0202020202020202022c020202"]},"v":{"chars":["‚Ėą ‚Ėą‚Ėą‚Ėą‚Ėą  ‚Ėą‚ĖÄ‚Ėą‚Ėą‚Ėą","‚Ėą‚Ėą‚Ėą‚Ėą‚Ėą‚Ėą ‚Ėą‚Ėą‚Ėą‚ĖĄ‚ĖÄ‚Ėą","‚Ėą‚Ėą‚Ėą‚Ėą ‚Ėą ‚Ėą‚Ėą‚Ė† ‚Ėą‚ĖĄ","‚ĖĄ‚ĖĄ‚ĖĄ‚ĖĄ‚ĖĄ‚ĖĄ ‚ĖĄ ‚ĖÄ‚ĖÄ‚ĖÄ‚ĖÄ","‚Ėą‚Ėą‚ĖĄ‚Ėą‚Ėą‚Ėą ‚Ėą‚Ėą‚Ėą‚Ėą‚Ėą‚Ėą","‚Ėź‚ĖÄ‚ĖĄ‚ĖÄ‚Ėą‚Ėą ‚Ėą‚ĖĄ‚ĖÄ‚ĖĄ‚Ėą‚ĖĆ"," ‚ĖÄ‚Ėą‚Ėą‚Ėą‚Ėą‚ĖĄ‚Ėą‚Ėą‚ĖÄ‚Ėą‚ĖÄ "],"colors":["011e01010101071e0119190909","01010101010107010101191919","010101011e01070101191e0119","02020202020207020701010101","02022c02020207020202020212","022c4c2c020207022c4c2c0202","0702020202020202022c020207"]},"w":{"chars":["‚Ėą ‚Ėą‚Ėą‚Ėą‚Ėą  ‚Ėą‚ĖÄ‚Ėą‚Ėą‚Ėą  ‚Ėą‚ĖÄ‚Ėą‚Ėą‚Ėą","‚Ėą‚Ėą‚Ėą‚Ėą‚Ėą‚Ėą ‚Ėą‚Ėą‚Ėą‚ĖĄ‚ĖÄ‚Ėą ‚Ėą‚Ėą‚Ėą‚ĖĄ‚ĖÄ‚Ėą","‚Ėą‚Ėą‚Ėą‚Ėą ‚Ėą ‚Ėą‚Ėą‚Ė† ‚Ėą‚ĖĄ ‚Ėą‚Ėą‚Ė† ‚Ėą‚ĖĄ","‚ĖĄ‚ĖĄ‚ĖĄ‚ĖĄ‚ĖĄ‚ĖĄ ‚ĖĄ ‚ĖÄ‚ĖÄ‚ĖÄ‚ĖÄ ‚ĖĄ ‚ĖÄ‚ĖÄ‚ĖÄ‚ĖÄ","‚Ėą‚Ėą‚ĖĄ‚Ėą‚Ėą‚Ėą ‚Ėą‚Ėą‚Ėą‚Ėą‚Ėą‚Ėą ‚Ėą‚Ėą‚Ėą‚Ėą‚Ėą‚Ėą","‚Ėą‚ĖÄ‚ĖĄ‚ĖÄ‚Ėą‚Ėą ‚Ėą‚ĖĄ‚ĖÄ‚ĖĄ‚Ėą‚Ėą ‚Ėą‚ĖĄ‚ĖÄ‚ĖĄ‚Ėą‚Ėą","‚ĖÄ‚Ėą‚Ėą‚Ėą‚Ėą‚Ėą‚ĖĄ‚Ėą‚Ėą‚ĖÄ‚ĖÄ‚Ėą‚Ėą‚ĖĄ‚Ėą‚Ėą‚ĖÄ‚Ėą‚Ėą‚ĖÄ"],"colors":["011e01010101071e0119190909071e0119190909","0101010101010701010119191907010101191919","010101011e01070101191e0119070101191e0119","0202020202020702070101010107020701010101","02022c0202020702020202021207020202020212","022c4c2c020207022c4c2c020207022c4c2c0202","020202020202020202020202020202022c020202"]},"x":{"chars":["‚Ėą ‚Ėą‚Ėą‚Ėą‚Ėą  ‚Ėą‚ĖÄ‚Ėą‚Ėą‚Ėą","‚Ėź‚Ėą‚Ėą‚Ėą‚Ėą‚Ėą ‚Ėą‚Ėą‚Ėą‚ĖĄ‚ĖÄ‚Ėą"," ‚ĖÄ‚Ėą‚Ėą ‚Ėą‚ĖĄ‚Ėą‚Ėą‚Ė† ‚Ėą ","   ‚ĖĄ‚ĖĄ‚ĖĄ ‚ĖĄ ‚ĖÄ‚ĖÄ  ","‚ĖĄ‚Ėą‚ĖĄ‚Ėą‚Ėą‚Ėą ‚Ėą‚Ėą‚Ėą‚Ėą‚Ėą‚ĖĄ","‚Ėą‚ĖÄ‚ĖĄ‚ĖÄ‚Ėą‚Ėą ‚Ėą‚ĖĄ‚ĖÄ‚ĖĄ‚Ėą‚Ėą","‚Ėą‚Ėą‚Ėą‚Ėą‚Ėą‚Ėą ‚Ėą‚Ėą‚ĖÄ‚Ėą‚Ėą‚Ėą"],"colors":["011e01010101071e0119190909","01010101010107010101191919","070101011e01010101191e0107","07070702020207020701010707","02022c02020207020202020202","022c4c2c020207022c4c2c0202","0202020202020702022c020202"]},"y":{"chars":["‚Ėą ‚Ėą‚Ėą‚Ėą‚Ėą  ‚Ėą‚ĖÄ‚Ėą‚Ėą‚Ėą","‚Ėą‚Ėą‚Ėą‚Ėą‚Ėą‚Ėą ‚Ėą‚Ėą‚Ėą‚ĖĄ‚ĖÄ‚Ėą","‚ĖÄ‚Ėą‚Ėą‚Ėą ‚Ėą‚ĖĄ‚Ėą‚Ėą‚Ė† ‚Ėą‚ĖĄ","       ‚ĖĄ ‚ĖÄ‚ĖÄ‚ĖÄ‚ĖÄ","‚Ėą‚Ėą‚ĖĄ‚Ėą‚Ėą‚Ėą ‚Ėą‚Ėą‚Ėą‚Ėą‚Ėą‚Ėą","‚Ėą‚ĖÄ‚ĖĄ‚ĖÄ‚Ėą‚Ėą ‚Ėą‚ĖĄ‚ĖÄ‚ĖĄ‚Ėą‚Ėą","‚Ėą‚Ėą‚Ėą‚Ėą‚Ėą‚Ėą‚ĖĄ‚Ėą‚Ėą‚ĖÄ‚Ėą‚Ėą‚ĖÄ"],"colors":["011e01010101071e0119190909","01010101010107010101191919","010101011e01010101191e0119","07070707070707020701010101","02022c02020207020202020212","022c4c2c020207022c4c2c0202","0202020202020202022c020202"]},"z":{"chars":["‚ĖÄ‚ĖÄ‚ĖÄ‚ĖÄ‚ĖÄ‚ĖÄ‚ĖÄ‚ĖÄ‚ĖÄ‚ĖÄ‚Ė†‚ĖÄ‚Ėą","‚ĖĄ‚ĖĄ‚ĖÄ‚Ėź‚Ėą‚Ėą‚ĖÄ‚ĖÄ‚ĖÄ‚ĖÄ‚ĖÄ‚ĖÄ‚ĖÄ"," ‚Ė† ‚Ėą‚Ėą‚Ėą ‚Ėą‚Ėą‚Ėą‚Ėą‚Ėą‚Ėą","‚ĖÄ ‚ĖĄ‚ĖĄ‚ĖĄ‚ĖĄ ‚ĖĄ‚ĖĄ‚ĖĄ‚ĖĄ‚ĖĄ‚ĖĄ","‚Ėą‚Ėą‚Ėą‚Ėą‚Ėą‚Ėą ‚Ėą‚Ėą ‚ĖĄ‚ĖÄ‚ĖĄ","‚Ėą‚Ėą‚Ėą‚Ėą‚Ėą‚Ėą ‚Ėą   ‚ĖÄ‚Ėą","‚ĖÄ‚Ėą‚ĖĄ‚ĖÄ‚ĖĄ‚Ėą‚ĖĄ‚Ėą‚Ėą‚Ėą‚Ėą‚Ėą‚ĖÄ"],"colors":["01010101010101010101191909","01191919190909010901010101","19191901011907010101010101","01070202020207020202020202","0202020202020702022c2c4c2c","02020202020207022c2c2c2c02","02022c4c2c0202020202020202"]}}}
