{"kind":"tdf-color","format":"tdf-compact-v1","key":"mirrow2.tdf","name":"Mirrow 2","height":11,"spacing":2,"colorSlots":["0x03","0x07","0x08","0x0b","0x0f","0x38","0x3b","0x3f","0x7b"],"glyphs":{"A":{"chars":["‚ĖĄ‚Ėď‚ĖÄ‚ĖÄ‚Ėą‚ĖĄ","‚ĖĎ‚Ėí  ‚Ėą‚Ėą"," ‚ĖĎ  ‚Ėď‚Ėą","    ‚Ėď‚Ėď","‚ĖĎ   ‚Ėą‚Ėď","‚ĖĎ‚ĖĎ  ‚Ėď‚Ėą","‚Ėí‚ĖĎ  ‚Ėí‚Ėď","‚Ėí‚Ėí‚ĖÄ‚ĖÄ‚ĖĎ ","‚Ėď‚Ėí   ‚ĖĎ","‚Ėď‚Ėď  ‚ĖĎ ","‚Ėą‚Ėď  ‚Ėí‚ĖĎ"],"colors":["0b3b0b0b3f0f","3b3b07073f3f","3b3b07073f3f","3b3b07073f3f","383807073b3f","383807073b3b","383807073b3b","383803033b3b","38380707383b","383807073838","383807073838"]},"B":{"chars":["‚Ėí‚Ėď‚ĖÄ‚ĖÄ‚Ėď‚ĖĄ","‚ĖĎ‚Ėí  ‚ĖĎ‚Ėí"," ‚ĖĎ   ‚ĖĎ","      ","‚ĖĎ   ‚ĖĎ ","‚ĖĎ‚ĖĎ  ‚Ėą‚Ėą","‚Ėí‚ĖĎ  ‚Ėí‚ĖĎ","‚Ėí‚Ėí ‚ĖÄ‚Ėí‚ĖĄ","‚Ėď‚Ėí  ‚Ėď‚Ėí","‚Ėď‚Ėď  ‚Ėď‚Ėď","‚Ėą‚Ėď‚ĖĄ‚ĖĄ‚Ėą‚ĖÄ"],"colors":["3b3b0b0b3b03","3b3b07073b3b","3b3b07073b3b","383807073838","383807073838","383807070303","383807073838","383807033803","383807073838","383807073838","383803033803"]},"C":{"chars":["‚Ėí‚Ėď‚ĖÄ‚Ėď‚Ėą","‚ĖĎ‚Ėí   "," ‚ĖĎ   ","     ","‚ĖĎ    ","‚ĖĎ‚ĖĎ   ","‚Ėí‚ĖĎ   ","‚Ėí‚Ėí   ","‚Ėď‚Ėí   ","‚Ėď‚Ėď   ","‚Ėą‚Ėď‚ĖĄ‚Ėď‚Ėí"],"colors":["3b3b0b3f3f","3b3b070707","3f3b070707","3f3f070707","3838070707","3838070707","3838070707","3838070707","3838070707","3838070707","3838083838"]},"D":{"chars":["‚Ėí‚Ėď‚ĖÄ‚ĖÄ‚Ėď‚ĖĄ","‚ĖĎ‚Ėí  ‚ĖĎ‚Ėí"," ‚ĖĎ   ‚ĖĎ","      ","‚ĖĎ   ‚ĖĎ ","‚ĖĎ‚ĖĎ  ‚ĖĎ‚ĖĎ","‚Ėí‚ĖĎ  ‚Ėí‚ĖĎ","‚Ėí‚Ėí  ‚Ėí‚Ėí","‚Ėď‚Ėí  ‚Ėď‚Ėí","‚Ėď‚Ėď  ‚Ėď‚Ėď","‚Ėą‚Ėď‚ĖĄ‚ĖĄ‚Ėą‚ĖÄ"],"colors":["3b3b0b0b3b03","3b3b07073b3b","3b3b07073b3b","383807073838","383807073838","383807073838","383807073838","383807073838","383807073838","383807073838","383803033803"]},"E":{"chars":["‚Ėí‚Ėď‚ĖÄ‚Ėď‚Ėą","‚ĖĎ‚Ėí   "," ‚ĖĎ   ","     ","‚ĖĎ    ","‚ĖĎ‚ĖĎ   ","‚Ėí‚ĖĎ   ","‚Ėí‚Ėí‚ĖÄ‚ĖÄ ","‚Ėď‚Ėí   ","‚Ėď‚Ėď   ","‚Ėą‚Ėď‚ĖĄ‚Ėď‚Ėí"],"colors":["3b3b0b3f3f","3b3b070707","3f3b070707","3f3f070707","3838070707","3838070707","3838070707","3838030307","3838070707","3838070707","3838083838"]},"F":{"chars":["‚Ėí‚Ėď‚ĖÄ‚Ėď‚Ėą","‚ĖĎ‚Ėí   "," ‚ĖĎ   ","     ","‚ĖĎ    ","‚ĖĎ‚ĖĎ   ","‚Ėí‚ĖĎ   ","‚Ėí‚Ėí‚ĖÄ‚ĖÄ ","‚Ėď‚Ėí   ","‚Ėď‚Ėď   ","‚Ėą‚Ėď   "],"colors":["3b3b0b3f3f","3b3b070707","3f3b070707","3f3f070707","3838070707","3838070707","3838070707","3838030307","3838070707","3838070707","3838070707"]},"G":{"chars":["‚Ėí‚Ėď‚ĖÄ‚Ėą‚Ėą‚ĖĄ","‚ĖĎ‚Ėí  ‚Ėą‚Ėą"," ‚ĖĎ  ‚Ėď‚Ėą","    ‚Ėď‚Ėď","‚ĖĎ   ‚Ėą‚Ėď","‚ĖĎ‚ĖĎ  ‚Ėď‚Ėą","‚Ėí‚ĖĎ    ","‚Ėí‚Ėí‚ĖÄ‚ĖÄ‚Ėą‚ĖĎ","‚Ėď‚Ėí  ‚ĖĎ‚Ėí","‚Ėď‚Ėď  ‚Ėí‚Ėď","‚Ėą‚Ėď‚Ėí‚Ėí‚Ėď‚Ėą"],"colors":["3b3b0b0f3f0f","3b3b07073f3f","3f3b07073f3f","3f3f07073f3f","383807073b3f","383807073b3b","383807070707","383808030338","383807073838","383807073838","383838383808"]},"H":{"chars":["‚Ėí‚Ėď  ‚Ėą‚Ėą","‚ĖĎ‚Ėí  ‚Ėą‚Ėą"," ‚ĖĎ  ‚Ėď‚Ėą","    ‚Ėď‚Ėď","‚ĖĎ   ‚Ėą‚Ėď","‚ĖĎ‚ĖĎ  ‚Ėď‚Ėą","‚Ėí‚ĖĎ  ‚Ėí‚Ėď","‚Ėí‚Ėí‚ĖÄ‚ĖÄ‚ĖĎ ","‚Ėď‚Ėí   ‚ĖĎ","‚Ėď‚Ėď  ‚ĖĎ ","‚Ėą‚Ėď  ‚Ėí‚ĖĎ"],"colors":["3b3b07073f0f","3b3b07073f3f","3b3b07073f3f","3b3b07073f3f","383807073b3f","383807073b3b","383807073b3b","383803033b3b","38380707383b","383807073838","383807073838"]},"I":{"chars":["‚ĖÄ‚ĖÄ","‚ĖĎ‚Ėí"," ‚ĖĎ","  ","‚ĖĎ ","‚ĖĎ‚ĖĎ","‚Ėí‚ĖĎ","‚Ėí‚Ėí","‚Ėď‚Ėí","‚Ėď‚Ėď","‚Ėą‚Ėď"],"colors":["0b0f","3b3b","3b3b","3b3b","3838","3838","3838","3838","3838","3838","3838"]},"J":{"chars":["   ‚Ėď‚Ėí","   ‚Ėí‚ĖĎ","   ‚ĖĎ ","     ","    ‚ĖĎ","   ‚ĖĎ‚ĖĎ","   ‚ĖĎ‚Ėí","   ‚Ėí‚Ėí","   ‚Ėí‚Ėď","   ‚Ėď‚Ėď","‚Ėí‚Ėď‚ĖĄ‚Ėď‚Ėą"],"colors":["0707073b3b","0707073b3b","0707073b3f","0707073f3f","0707073838","0707073838","0707073838","0707073838","0707073838","0707073838","3838083838"]},"K":{"chars":["‚Ėí‚Ėď  ‚Ėą‚Ėą","‚ĖĎ‚Ėí  ‚Ėą‚Ėą"," ‚ĖĎ  ‚Ėď‚Ėą","    ‚Ėď‚Ėď","‚ĖĎ   ‚Ėą‚Ėď","‚ĖĎ‚ĖĎ  ‚Ėď‚Ėą","‚Ėí‚ĖĎ  ‚Ėí‚Ėď","‚Ėí‚Ėí‚ĖÄ‚ĖÄ‚ĖĎ‚ĖĄ","‚Ėď‚Ėí   ‚ĖĎ","‚Ėď‚Ėď  ‚ĖĎ ","‚Ėą‚Ėď  ‚Ėí‚ĖĎ"],"colors":["3b3b07073f0f","3b3b07073f3f","3b3b07073f3f","3b3b07073f3f","383807073b3f","383807073b3b","383807073b3b","383803033b03","38380707383b","383807073838","383807073838"]},"L":{"chars":["‚Ėí‚Ėď   ","‚ĖĎ‚Ėí   "," ‚ĖĎ   ","     ","‚ĖĎ    ","‚ĖĎ‚ĖĎ   ","‚Ėí‚ĖĎ   ","‚Ėí‚Ėí   ","‚Ėď‚Ėí   ","‚Ėď‚Ėď   ","‚Ėą‚Ėď‚ĖĄ‚Ėď‚Ėí"],"colors":["3b3b070707","3b3b070707","3f3b070707","3f3f070707","3838070707","3838070707","3838070707","3838070707","3838070707","3838070707","3838083838"]},"M":{"chars":["‚Ėí‚Ėď‚ĖÄ‚Ėď‚Ėą‚ĖĄ‚Ėď‚ĖÄ‚Ėą‚Ėí","‚ĖĎ‚Ėí  ‚Ėą‚Ėą  ‚Ėí‚Ėď"," ‚ĖĎ  ‚Ėď‚Ėą  ‚Ėď‚Ėď","    ‚Ėď‚Ėď  ‚Ėí‚Ėí","‚ĖĎ   ‚Ėą‚Ėď  ‚Ėí‚ĖĎ","‚ĖĎ‚ĖĎ  ‚Ėď‚Ėą  ‚ĖĎ ","‚Ėí‚ĖĎ  ‚Ėí‚Ėď    ","‚Ėí‚Ėí  ‚ĖĎ    ‚ĖĎ","‚Ėď‚Ėí   ‚Ėí  ‚ĖĎ‚Ėí","‚Ėď‚Ėď  ‚ĖĎ   ‚Ėí‚Ėď","‚Ėą‚Ėď  ‚Ėí‚Ėď  ‚Ėď‚Ėą"],"colors":["3b3b0b3f3f0f3f0b7b7b","3b3b07073f3f07077b3b","383b07073f3f07073b3b","383807073f3f07073b3b","383807073b3f07073b3b","383807073b3b07073b3b","383807073b3b07073b3b","383807073b3b07073b38","38380707383807073838","38380707383807073838","38380707383807073808"]},"N":{"chars":["‚Ėí‚Ėď‚ĖÄ‚ĖÄ‚Ėď‚ĖĄ","‚ĖĎ‚Ėí  ‚ĖĎ‚Ėí"," ‚ĖĎ   ‚ĖĎ","      ","‚ĖĎ   ‚ĖĎ ","‚ĖĎ‚ĖĎ  ‚ĖĎ‚ĖĎ","‚Ėí‚ĖĎ  ‚Ėí‚ĖĎ","‚Ėí‚Ėí  ‚Ėí‚Ėí","‚Ėď‚Ėí  ‚Ėď‚Ėí","‚Ėď‚Ėď  ‚Ėď‚Ėď","‚Ėą‚Ėď  ‚Ėą‚Ėď"],"colors":["3b3b0b0b3b03","3b3b07073b3b","3b3b07073b3b","383807073838","383807073838","383807073838","383807073838","383807073838","383807073838","383807073838","383807073838"]},"O":{"chars":["‚Ėí‚Ėď‚ĖÄ‚ĖÄ‚Ėď‚Ėí","‚ĖĎ‚Ėí  ‚ĖĎ‚Ėí"," ‚ĖĎ   ‚ĖĎ","      ","‚ĖĎ   ‚ĖĎ ","‚ĖĎ‚ĖĎ  ‚ĖĎ‚ĖĎ","‚Ėí‚ĖĎ  ‚Ėí‚ĖĎ","‚Ėí‚Ėí  ‚Ėí‚Ėí","‚Ėď‚Ėí  ‚Ėď‚Ėí","‚Ėď‚Ėď  ‚Ėď‚Ėď","‚Ėą‚Ėď‚ĖĄ‚ĖĄ‚Ėą‚Ėď"],"colors":["3b3b0b0b3b3b","3b3b07073b3b","3b3b07073b3b","383807073838","383807073838","383807073838","383807073838","383807073838","383807073838","383807073838","383803033838"]},"P":{"chars":["‚Ėą‚Ėą‚ĖÄ‚ĖÄ‚Ėď‚ĖĄ","‚ĖĎ‚Ėí  ‚ĖĎ‚Ėí"," ‚ĖĎ   ‚ĖĎ","      ","‚ĖĎ ‚ĖÄ‚ĖÄ‚ĖÄ ","‚ĖĎ‚ĖĎ    ","‚Ėí‚ĖĎ    ","‚Ėí‚Ėí    ","‚Ėď‚Ėí    ","‚Ėď‚Ėď    ","‚Ėą‚Ėď    "],"colors":["030303033b03","3b3b07073b3b","3b3b07073b3b","383807073838","383808030307","383807070707","383807070707","383807070707","383807070707","383807070707","383807070707"]},"Q":{"chars":["‚Ėí‚Ėď‚ĖÄ‚ĖÄ‚Ėď‚Ėí","‚ĖĎ‚Ėí  ‚ĖĎ‚Ėí"," ‚ĖĎ   ‚ĖĎ","      ","‚ĖĎ   ‚ĖĎ ","‚ĖĎ‚ĖĎ  ‚ĖĎ‚ĖĎ","‚Ėí‚ĖĎ  ‚Ėí‚ĖĎ","‚Ėí‚Ėí  ‚Ėí‚Ėí","‚Ėď‚Ėí  ‚Ėď‚Ėí","‚Ėď‚Ėď‚Ėź‚ĖĄ‚Ėď‚Ėď","‚Ėą‚Ėď‚ĖĄ‚Ėą‚Ėą‚Ėď"],"colors":["3b3b0b0b3b3b","3b3b07073b3b","3b3b07073b3b","383807073838","383807073838","383807073838","383807073838","383807073838","383807073838","383808083838","383808083838"]},"R":{"chars":["‚Ėą‚Ėą‚ĖÄ‚ĖÄ‚Ėď‚ĖĄ","‚ĖĎ‚Ėí  ‚ĖĎ‚Ėí"," ‚ĖĎ   ‚ĖĎ","      ","‚ĖĎ  ‚ĖÄ‚Ėą‚ĖĄ","‚ĖĎ‚ĖĎ  ‚ĖĎ‚Ėą","‚Ėí‚ĖĎ  ‚Ėí‚ĖĎ","‚Ėí‚Ėí  ‚Ėí‚Ėí","‚Ėď‚Ėí  ‚Ėď‚Ėí","‚Ėď‚Ėď  ‚Ėď‚Ėď","‚Ėą‚Ėď  ‚Ėą‚Ėď"],"colors":["030303033b03","3b3b07073b3b","3b3b07073b3b","383807073838","383807030303","383807073803","383807073838","383807073838","383807073838","383807073838","383807073838"]},"S":{"chars":["‚ĖĄ‚Ėď‚ĖÄ‚ĖÄ‚Ėą‚Ėą","‚ĖĎ‚Ėí  ‚Ėą‚Ėą"," ‚ĖĎ  ‚Ėď‚Ėą","    ‚Ėď‚Ėď","‚ĖĎ   ‚Ėą‚Ėď","‚ĖĎ‚ĖĎ  ‚Ėď‚Ėą","‚Ėí‚ĖĎ    "," ‚ĖÄ‚ĖÄ‚ĖÄ‚ĖĎ‚ĖĄ","‚Ėď‚Ėí   ‚ĖĎ","‚Ėď‚Ėď  ‚ĖĎ ","‚Ėą‚Ėď‚ĖĄ‚ĖĄ‚Ėí‚ĖÄ"],"colors":["033b0b0b3f0f","3b3b07073f3f","3b3b07073f3f","3b3b07073f3f","383807073b3f","383807073b3b","383807070707","070303033b03","38380707383b","383807073838","383808083803"]},"T":{"chars":["‚Ėą‚Ėą‚ĖÄ‚Ėí‚Ėď‚ĖÄ‚Ėď‚Ėą","   ‚ĖĎ‚Ėí   ","    ‚ĖĎ   ","        ","   ‚ĖĎ    ","   ‚ĖĎ‚ĖĎ   ","   ‚Ėí‚ĖĎ   ","   ‚Ėí‚Ėí   ","   ‚Ėď‚Ėí   ","   ‚Ėď‚Ėď   ","   ‚Ėą‚Ėď   "],"colors":["0b0b0b3b3b0b3f3f","0707073b3b070707","0707073f3b070707","0707073f3f070707","0707073838070707","0707073838070707","0707073838070707","0707073838070707","0707073838070707","0707073838070707","0707073838070707"]},"U":{"chars":["‚Ėí‚Ėď  ‚Ėď‚Ėí","‚ĖĎ‚Ėí  ‚ĖĎ‚Ėí"," ‚ĖĎ   ‚ĖĎ","      ","‚ĖĎ   ‚ĖĎ ","‚ĖĎ‚ĖĎ  ‚ĖĎ‚ĖĎ","‚Ėí‚ĖĎ  ‚Ėí‚ĖĎ","‚Ėí‚Ėí  ‚Ėí‚Ėí","‚Ėď‚Ėí  ‚Ėď‚Ėí","‚Ėď‚Ėď  ‚Ėď‚Ėď","‚ĖÄ‚Ėď‚ĖĄ‚ĖĄ‚Ėą‚ĖÄ"],"colors":["3b3b07073b3b","3b3b07073b3b","3b3b07073b3b","383807073838","383807073838","383807073838","383807073838","383807073838","383807073838","383807073838","083803033808"]},"V":{"chars":["‚Ėí‚Ėď  ‚Ėď‚Ėí","‚ĖĎ‚Ėí  ‚ĖĎ‚Ėí"," ‚ĖĎ   ‚ĖĎ","      ","‚ĖĎ   ‚ĖĎ ","‚ĖĎ‚ĖĎ  ‚ĖĎ‚ĖĎ","‚Ėí‚ĖĎ  ‚Ėí‚ĖĎ","‚Ėí‚Ėí  ‚Ėí‚Ėí","‚Ėď‚Ėí  ‚Ėď‚Ėí","‚Ėź‚Ėď‚ĖĆ‚Ėź‚Ėď‚ĖĆ"," ‚ĖÄ‚Ėą‚Ėą‚ĖÄ "],"colors":["3b3b07073b3b","3b3b07073b3b","3b3b07073b3b","383807073838","383807073838","383807073838","383807073838","383807073838","383807073838","083808083808","070808080807"]},"W":{"chars":["‚Ėí‚Ėď      ‚Ėď‚Ėí","‚ĖĎ‚Ėí      ‚ĖĎ‚Ėí"," ‚ĖĎ       ‚ĖĎ","          ","‚ĖĎ   ‚ĖĎ   ‚ĖĎ ","‚ĖĎ‚ĖĎ  ‚ĖĎ‚ĖĎ  ‚ĖĎ‚ĖĎ","‚Ėí‚ĖĎ  ‚Ėí‚ĖĎ  ‚Ėí‚ĖĎ","‚Ėí‚Ėí  ‚Ėí‚Ėí  ‚Ėí‚Ėí","‚Ėď‚Ėí  ‚Ėď‚Ėí  ‚Ėď‚Ėí","‚Ėď‚Ėď  ‚Ėď‚Ėď  ‚Ėď‚Ėď","‚Ėą‚Ėď‚ĖĄ‚ĖĄ‚Ėą‚Ėď‚ĖĄ‚ĖĄ‚Ėą‚Ėď"],"colors":["3b3b0707070707073b3b","3b3b0707070707073b3b","3b3b0707070707073b3b","38380707383807073838","38380707383807073838","38380707383807073838","38380707383807073838","38380707383807073838","38380707383807073838","38380707383807073838","38380303383803033838"]},"X":{"chars":["‚Ėí‚Ėď  ‚Ėą‚Ėą","‚ĖĎ‚Ėí  ‚Ėą‚Ėą"," ‚ĖĎ  ‚Ėď‚Ėą","    ‚Ėď‚Ėď","‚ĖĎ   ‚Ėą‚Ėď","‚ĖĎ‚ĖĎ  ‚Ėď‚Ėą","‚Ėí‚ĖĎ  ‚Ėí‚Ėď","‚ĖĄ‚Ėí‚ĖÄ‚ĖÄ‚ĖĎ‚ĖĄ","‚Ėď‚Ėí   ‚ĖĎ","‚Ėď‚Ėď  ‚ĖĎ ","‚Ėą‚Ėď  ‚Ėí‚ĖĎ"],"colors":["3b3b07073f0f","3b3b07073f3f","3b3b07073f3f","3b3b07073f3f","383807073b3f","383807073b3b","383807073b3b","033803033b03","38380707383b","383807073838","383807073838"]},"Y":{"chars":["‚Ėí‚Ėď  ‚Ėą‚Ėą","‚ĖĎ‚Ėí  ‚Ėą‚Ėą"," ‚ĖĎ  ‚Ėď‚Ėą","    ‚Ėď‚Ėď","‚ĖĎ   ‚Ėą‚Ėď","‚ĖĎ‚ĖĎ  ‚Ėď‚Ėą","‚Ėí‚ĖĎ  ‚Ėí‚Ėď"," ‚ĖÄ‚ĖÄ‚ĖÄ‚ĖĎ ","‚Ėď‚Ėí   ‚ĖĎ","‚Ėď‚Ėď  ‚ĖĎ ","‚Ėą‚Ėď‚ĖĄ‚ĖĄ‚Ėí‚ĖÄ"],"colors":["3b3b07073f0f","3b3b07073f3f","3b3b07073f3f","3b3b07073f3f","383807073b3f","383807073b3b","383807073b3b","070303033b3b","38380707383b","383807073838","383808083803"]},"Z":{"chars":["‚Ėą‚Ėą‚ĖÄ‚ĖÄ‚Ėď‚ĖĄ","‚Ėą‚Ėą  ‚Ėí‚ĖĎ","‚Ėą‚Ėď  ‚ĖĎ ","‚Ėď‚Ėď    ","‚Ėď‚Ėą   ‚ĖĎ","‚Ėą‚Ėď  ‚ĖĎ‚ĖĎ","    ‚ĖĎ‚Ėí","‚ĖĄ‚ĖĎ‚ĖÄ‚ĖÄ‚ĖÄ ","‚ĖĎ   ‚Ėí‚Ėď"," ‚ĖĎ  ‚Ėď‚Ėď","‚ĖÄ‚Ėí‚ĖĄ‚ĖĄ‚Ėď‚Ėą"],"colors":["0f3f0b0b3b03","3f3f07073b3b","3f3f07073b3b","3f3f07073b3b","3f3b07073838","3b3b07073838","070707073838","033b03030307","3b3807073838","383807073838","033808083838"]},"a":{"chars":["‚ĖĄ‚Ėď‚ĖÄ‚ĖÄ‚Ėą‚ĖĄ","‚ĖĎ‚Ėí  ‚Ėą‚Ėą"," ‚ĖĎ  ‚Ėď‚Ėą","    ‚Ėď‚Ėď","‚ĖĎ   ‚Ėą‚Ėď","‚ĖĎ‚ĖĎ  ‚Ėď‚Ėą","‚Ėí‚ĖĎ  ‚Ėí‚Ėď","‚Ėí‚Ėí‚ĖÄ‚ĖÄ‚ĖĎ ","‚Ėď‚Ėí   ‚ĖĎ","‚Ėď‚Ėď  ‚ĖĎ ","‚Ėą‚Ėď  ‚Ėí‚ĖĎ"],"colors":["0b3b0b0b3f0f","3b3b07073f3f","3b3b07073f3f","3b3b07073f3f","383807073b3f","383807073b3b","383807073b3b","383803033b3b","38380707383b","383807073838","383807073838"]},"b":{"chars":["‚Ėí‚Ėď‚ĖÄ‚ĖÄ‚Ėď‚ĖĄ","‚ĖĎ‚Ėí  ‚ĖĎ‚Ėí"," ‚ĖĎ   ‚ĖĎ","      ","‚ĖĎ   ‚ĖĎ ","‚ĖĎ‚ĖĎ  ‚Ėą‚Ėą","‚Ėí‚ĖĎ  ‚Ėí‚ĖĎ","‚Ėí‚Ėí ‚ĖÄ‚Ėí‚ĖĄ","‚Ėď‚Ėí  ‚Ėď‚Ėí","‚Ėď‚Ėď  ‚Ėď‚Ėď","‚Ėą‚Ėď‚ĖĄ‚ĖĄ‚Ėą‚ĖÄ"],"colors":["3b3b0b0b3b03","3b3b07073b3b","3b3b07073b3b","383807073838","383807073838","383807070303","383807073838","383807033803","383807073838","383807073838","383803033803"]},"c":{"chars":["‚Ėí‚Ėď‚ĖÄ‚Ėď‚Ėą","‚ĖĎ‚Ėí   "," ‚ĖĎ   ","     ","‚ĖĎ    ","‚ĖĎ‚ĖĎ   ","‚Ėí‚ĖĎ   ","‚Ėí‚Ėí   ","‚Ėď‚Ėí   ","‚Ėď‚Ėď   ","‚Ėą‚Ėď‚ĖĄ‚Ėď‚Ėí"],"colors":["3b3b0b3f3f","3b3b070707","3f3b070707","3f3f070707","3838070707","3838070707","3838070707","3838070707","3838070707","3838070707","3838083838"]},"d":{"chars":["‚Ėí‚Ėď‚ĖÄ‚ĖÄ‚Ėď‚ĖĄ","‚ĖĎ‚Ėí  ‚ĖĎ‚Ėí"," ‚ĖĎ   ‚ĖĎ","      ","‚ĖĎ   ‚ĖĎ ","‚ĖĎ‚ĖĎ  ‚ĖĎ‚ĖĎ","‚Ėí‚ĖĎ  ‚Ėí‚ĖĎ","‚Ėí‚Ėí  ‚Ėí‚Ėí","‚Ėď‚Ėí  ‚Ėď‚Ėí","‚Ėď‚Ėď  ‚Ėď‚Ėď","‚Ėą‚Ėď‚ĖĄ‚ĖĄ‚Ėą‚ĖÄ"],"colors":["3b3b0b0b3b03","3b3b07073b3b","3b3b07073b3b","383807073838","383807073838","383807073838","383807073838","383807073838","383807073838","383807073838","383803033803"]},"e":{"chars":["‚Ėí‚Ėď‚ĖÄ‚Ėď‚Ėą","‚ĖĎ‚Ėí   "," ‚ĖĎ   ","     ","‚ĖĎ    ","‚ĖĎ‚ĖĎ   ","‚Ėí‚ĖĎ   ","‚Ėí‚Ėí‚ĖÄ‚ĖÄ ","‚Ėď‚Ėí   ","‚Ėď‚Ėď   ","‚Ėą‚Ėď‚ĖĄ‚Ėď‚Ėí"],"colors":["3b3b0b3f3f","3b3b070707","3f3b070707","3f3f070707","3838070707","3838070707","3838070707","3838030307","3838070707","3838070707","3838083838"]},"f":{"chars":["‚Ėí‚Ėď‚ĖÄ‚Ėď‚Ėą","‚ĖĎ‚Ėí   "," ‚ĖĎ   ","     ","‚ĖĎ    ","‚ĖĎ‚ĖĎ   ","‚Ėí‚ĖĎ   ","‚Ėí‚Ėí‚ĖÄ‚ĖÄ ","‚Ėď‚Ėí   ","‚Ėď‚Ėď   ","‚Ėą‚Ėď   "],"colors":["3b3b0b3f3f","3b3b070707","3f3b070707","3f3f070707","3838070707","3838070707","3838070707","3838030307","3838070707","3838070707","3838070707"]},"g":{"chars":["‚Ėí‚Ėď‚ĖÄ‚Ėą‚Ėą‚ĖĄ","‚ĖĎ‚Ėí  ‚Ėą‚Ėą"," ‚ĖĎ  ‚Ėď‚Ėą","    ‚Ėď‚Ėď","‚ĖĎ   ‚Ėą‚Ėď","‚ĖĎ‚ĖĎ  ‚Ėď‚Ėą","‚Ėí‚ĖĎ    ","‚Ėí‚Ėí‚ĖÄ‚ĖÄ‚Ėą‚ĖĎ","‚Ėď‚Ėí  ‚ĖĎ‚Ėí","‚Ėď‚Ėď  ‚Ėí‚Ėď","‚Ėą‚Ėď‚Ėí‚Ėí‚Ėď‚Ėą"],"colors":["3b3b0b0f3f0f","3b3b07073f3f","3f3b07073f3f","3f3f07073f3f","383807073b3f","383807073b3b","383807070707","383808030338","383807073838","383807073838","383838383808"]},"h":{"chars":["‚Ėí‚Ėď  ‚Ėą‚Ėą","‚ĖĎ‚Ėí  ‚Ėą‚Ėą"," ‚ĖĎ  ‚Ėď‚Ėą","    ‚Ėď‚Ėď","‚ĖĎ   ‚Ėą‚Ėď","‚ĖĎ‚ĖĎ  ‚Ėď‚Ėą","‚Ėí‚ĖĎ  ‚Ėí‚Ėď","‚Ėí‚Ėí‚ĖÄ‚ĖÄ‚ĖĎ ","‚Ėď‚Ėí   ‚ĖĎ","‚Ėď‚Ėď  ‚ĖĎ ","‚Ėą‚Ėď  ‚Ėí‚ĖĎ"],"colors":["3b3b07073f0f","3b3b07073f3f","3b3b07073f3f","3b3b07073f3f","383807073b3f","383807073b3b","383807073b3b","383803033b3b","38380707383b","383807073838","383807073838"]},"i":{"chars":["‚ĖÄ‚ĖÄ","‚ĖĎ‚Ėí"," ‚ĖĎ","  ","‚ĖĎ ","‚ĖĎ‚ĖĎ","‚Ėí‚ĖĎ","‚Ėí‚Ėí","‚Ėď‚Ėí","‚Ėď‚Ėď","‚Ėą‚Ėď"],"colors":["0b0f","3b3b","3b3b","3b3b","3838","3838","3838","3838","3838","3838","3838"]},"j":{"chars":["   ‚Ėď‚Ėí","   ‚Ėí‚ĖĎ","   ‚ĖĎ ","     ","    ‚ĖĎ","   ‚ĖĎ‚ĖĎ","   ‚ĖĎ‚Ėí","   ‚Ėí‚Ėí","   ‚Ėí‚Ėď","   ‚Ėď‚Ėď","‚Ėí‚Ėď‚ĖĄ‚Ėď‚Ėą"],"colors":["0707073b3b","0707073b3b","0707073b3f","0707073f3f","0707073838","0707073838","0707073838","0707073838","0707073838","0707073838","3838083838"]},"k":{"chars":["‚Ėí‚Ėď  ‚Ėą‚Ėą","‚ĖĎ‚Ėí  ‚Ėą‚Ėą"," ‚ĖĎ  ‚Ėď‚Ėą","    ‚Ėď‚Ėď","‚ĖĎ   ‚Ėą‚Ėď","‚ĖĎ‚ĖĎ  ‚Ėď‚Ėą","‚Ėí‚ĖĎ  ‚Ėí‚Ėď","‚Ėí‚Ėí‚ĖÄ‚ĖÄ‚ĖĎ‚ĖĄ","‚Ėď‚Ėí   ‚ĖĎ","‚Ėď‚Ėď  ‚ĖĎ ","‚Ėą‚Ėď  ‚Ėí‚ĖĎ"],"colors":["3b3b07073f0f","3b3b07073f3f","3b3b07073f3f","3b3b07073f3f","383807073b3f","383807073b3b","383807073b3b","383803033b03","38380707383b","383807073838","383807073838"]},"l":{"chars":["‚Ėí‚Ėď   ","‚ĖĎ‚Ėí   "," ‚ĖĎ   ","     ","‚ĖĎ    ","‚ĖĎ‚ĖĎ   ","‚Ėí‚ĖĎ   ","‚Ėí‚Ėí   ","‚Ėď‚Ėí   ","‚Ėď‚Ėď   ","‚Ėą‚Ėď‚ĖĄ‚Ėď‚Ėí"],"colors":["3b3b070707","3b3b070707","3f3b070707","3f3f070707","3838070707","3838070707","3838070707","3838070707","3838070707","3838070707","3838083838"]},"m":{"chars":["‚Ėí‚Ėď‚ĖÄ‚Ėď‚Ėą‚ĖĄ‚Ėď‚ĖÄ‚Ėą‚Ėí","‚ĖĎ‚Ėí  ‚Ėą‚Ėą  ‚Ėí‚Ėď"," ‚ĖĎ  ‚Ėď‚Ėą  ‚Ėď‚Ėď","    ‚Ėď‚Ėď  ‚Ėí‚Ėí","‚ĖĎ   ‚Ėą‚Ėď  ‚Ėí‚ĖĎ","‚ĖĎ‚ĖĎ  ‚Ėď‚Ėą  ‚ĖĎ ","‚Ėí‚ĖĎ  ‚Ėí‚Ėď    ","‚Ėí‚Ėí  ‚ĖĎ    ‚ĖĎ","‚Ėď‚Ėí   ‚Ėí  ‚ĖĎ‚Ėí","‚Ėď‚Ėď  ‚ĖĎ   ‚Ėí‚Ėď","‚Ėą‚Ėď  ‚Ėí‚Ėď  ‚Ėď‚Ėą"],"colors":["3b3b0b3f3f0f3f0b7b7b","3b3b07073f3f07077b3b","383b07073f3f07073b3b","383807073f3f07073b3b","383807073b3f07073b3b","383807073b3b07073b3b","383807073b3b07073b3b","383807073b3b07073b38","38380707383807073838","38380707383807073838","38380707383807073808"]},"n":{"chars":["‚Ėí‚Ėď‚ĖÄ‚ĖÄ‚Ėď‚ĖĄ","‚ĖĎ‚Ėí  ‚ĖĎ‚Ėí"," ‚ĖĎ   ‚ĖĎ","      ","‚ĖĎ   ‚ĖĎ ","‚ĖĎ‚ĖĎ  ‚ĖĎ‚ĖĎ","‚Ėí‚ĖĎ  ‚Ėí‚ĖĎ","‚Ėí‚Ėí  ‚Ėí‚Ėí","‚Ėď‚Ėí  ‚Ėď‚Ėí","‚Ėď‚Ėď  ‚Ėď‚Ėď","‚Ėą‚Ėď  ‚Ėą‚Ėď"],"colors":["3b3b0b0b3b03","3b3b07073b3b","3b3b07073b3b","383807073838","383807073838","383807073838","383807073838","383807073838","383807073838","383807073838","383807073838"]},"o":{"chars":["‚Ėí‚Ėď‚ĖÄ‚ĖÄ‚Ėď‚Ėí","‚ĖĎ‚Ėí  ‚ĖĎ‚Ėí"," ‚ĖĎ   ‚ĖĎ","      ","‚ĖĎ   ‚ĖĎ ","‚ĖĎ‚ĖĎ  ‚ĖĎ‚ĖĎ","‚Ėí‚ĖĎ  ‚Ėí‚ĖĎ","‚Ėí‚Ėí  ‚Ėí‚Ėí","‚Ėď‚Ėí  ‚Ėď‚Ėí","‚Ėď‚Ėď  ‚Ėď‚Ėď","‚Ėą‚Ėď‚ĖĄ‚ĖĄ‚Ėą‚Ėď"],"colors":["3b3b0b0b3b3b","3b3b07073b3b","3b3b07073b3b","383807073838","383807073838","383807073838","383807073838","383807073838","383807073838","383807073838","383803033838"]},"p":{"chars":["‚Ėą‚Ėą‚ĖÄ‚ĖÄ‚Ėď‚ĖĄ","‚ĖĎ‚Ėí  ‚ĖĎ‚Ėí"," ‚ĖĎ   ‚ĖĎ","      ","‚ĖĎ ‚ĖÄ‚ĖÄ‚ĖÄ ","‚ĖĎ‚ĖĎ    ","‚Ėí‚ĖĎ    ","‚Ėí‚Ėí    ","‚Ėď‚Ėí    ","‚Ėď‚Ėď    ","‚Ėą‚Ėď    "],"colors":["030303033b03","3b3b07073b3b","3b3b07073b3b","383807073838","383808030307","383807070707","383807070707","383807070707","383807070707","383807070707","383807070707"]},"q":{"chars":["‚Ėí‚Ėď‚ĖÄ‚ĖÄ‚Ėď‚Ėí","‚ĖĎ‚Ėí  ‚ĖĎ‚Ėí"," ‚ĖĎ   ‚ĖĎ","      ","‚ĖĎ   ‚ĖĎ ","‚ĖĎ‚ĖĎ  ‚ĖĎ‚ĖĎ","‚Ėí‚ĖĎ  ‚Ėí‚ĖĎ","‚Ėí‚Ėí  ‚Ėí‚Ėí","‚Ėď‚Ėí  ‚Ėď‚Ėí","‚Ėď‚Ėď‚Ėź‚ĖĄ‚Ėď‚Ėď","‚Ėą‚Ėď‚ĖĄ‚Ėą‚Ėą‚Ėď"],"colors":["3b3b0b0b3b3b","3b3b07073b3b","3b3b07073b3b","383807073838","383807073838","383807073838","383807073838","383807073838","383807073838","383808083838","383808083838"]},"r":{"chars":["‚Ėą‚Ėą‚ĖÄ‚ĖÄ‚Ėď‚ĖĄ","‚ĖĎ‚Ėí  ‚ĖĎ‚Ėí"," ‚ĖĎ   ‚ĖĎ","      ","‚ĖĎ  ‚ĖÄ‚Ėą‚ĖĄ","‚ĖĎ‚ĖĎ  ‚ĖĎ‚Ėą","‚Ėí‚ĖĎ  ‚Ėí‚ĖĎ","‚Ėí‚Ėí  ‚Ėí‚Ėí","‚Ėď‚Ėí  ‚Ėď‚Ėí","‚Ėď‚Ėď  ‚Ėď‚Ėď","‚Ėą‚Ėď  ‚Ėą‚Ėď"],"colors":["030303033b03","3b3b07073b3b","3b3b07073b3b","383807073838","383807030303","383807073803","383807073838","383807073838","383807073838","383807073838","383807073838"]},"s":{"chars":["‚ĖĄ‚Ėď‚ĖÄ‚ĖÄ‚Ėą‚Ėą","‚ĖĎ‚Ėí  ‚Ėą‚Ėą"," ‚ĖĎ  ‚Ėď‚Ėą","    ‚Ėď‚Ėď","‚ĖĎ   ‚Ėą‚Ėď","‚ĖĎ‚ĖĎ  ‚Ėď‚Ėą","‚Ėí‚ĖĎ    "," ‚ĖÄ‚ĖÄ‚ĖÄ‚ĖĎ‚ĖĄ","‚Ėď‚Ėí   ‚ĖĎ","‚Ėď‚Ėď  ‚ĖĎ ","‚Ėą‚Ėď‚ĖĄ‚ĖĄ‚Ėí‚ĖÄ"],"colors":["033b0b0b3f0f","3b3b07073f3f","3b3b07073f3f","3b3b07073f3f","383807073b3f","383807073b3b","383807070707","070303033b03","38380707383b","383807073838","383808083803"]},"t":{"chars":["‚Ėą‚Ėą‚ĖÄ‚Ėí‚Ėď‚ĖÄ‚Ėď‚Ėą","   ‚ĖĎ‚Ėí   ","    ‚ĖĎ   ","        ","   ‚ĖĎ    ","   ‚ĖĎ‚ĖĎ   ","   ‚Ėí‚ĖĎ   ","   ‚Ėí‚Ėí   ","   ‚Ėď‚Ėí   ","   ‚Ėď‚Ėď   ","   ‚Ėą‚Ėď   "],"colors":["0b0b0b3b3b0b3f3f","0707073b3b070707","0707073f3b070707","0707073f3f070707","0707073838070707","0707073838070707","0707073838070707","0707073838070707","0707073838070707","0707073838070707","0707073838070707"]},"u":{"chars":["‚Ėí‚Ėď  ‚Ėď‚Ėí","‚ĖĎ‚Ėí  ‚ĖĎ‚Ėí"," ‚ĖĎ   ‚ĖĎ","      ","‚ĖĎ   ‚ĖĎ ","‚ĖĎ‚ĖĎ  ‚ĖĎ‚ĖĎ","‚Ėí‚ĖĎ  ‚Ėí‚ĖĎ","‚Ėí‚Ėí  ‚Ėí‚Ėí","‚Ėď‚Ėí  ‚Ėď‚Ėí","‚Ėď‚Ėď  ‚Ėď‚Ėď","‚ĖÄ‚Ėď‚ĖĄ‚ĖĄ‚Ėą‚ĖÄ"],"colors":["3b3b07073b3b","3b3b07073b3b","3b3b07073b3b","383807073838","383807073838","383807073838","383807073838","383807073838","383807073838","383807073838","083803033808"]},"v":{"chars":["‚Ėí‚Ėď  ‚Ėď‚Ėí","‚ĖĎ‚Ėí  ‚ĖĎ‚Ėí"," ‚ĖĎ   ‚ĖĎ","      ","‚ĖĎ   ‚ĖĎ ","‚ĖĎ‚ĖĎ  ‚ĖĎ‚ĖĎ","‚Ėí‚ĖĎ  ‚Ėí‚ĖĎ","‚Ėí‚Ėí  ‚Ėí‚Ėí","‚Ėď‚Ėí  ‚Ėď‚Ėí","‚Ėź‚Ėď‚ĖĆ‚Ėź‚Ėď‚ĖĆ"," ‚ĖÄ‚Ėą‚Ėą‚ĖÄ "],"colors":["3b3b07073b3b","3b3b07073b3b","3b3b07073b3b","383807073838","383807073838","383807073838","383807073838","383807073838","383807073838","083808083808","070808080807"]},"w":{"chars":["‚Ėí‚Ėď      ‚Ėď‚Ėí","‚ĖĎ‚Ėí      ‚ĖĎ‚Ėí"," ‚ĖĎ       ‚ĖĎ","          ","‚ĖĎ   ‚ĖĎ   ‚ĖĎ ","‚ĖĎ‚ĖĎ  ‚ĖĎ‚ĖĎ  ‚ĖĎ‚ĖĎ","‚Ėí‚ĖĎ  ‚Ėí‚ĖĎ  ‚Ėí‚ĖĎ","‚Ėí‚Ėí  ‚Ėí‚Ėí  ‚Ėí‚Ėí","‚Ėď‚Ėí  ‚Ėď‚Ėí  ‚Ėď‚Ėí","‚Ėď‚Ėď  ‚Ėď‚Ėď  ‚Ėď‚Ėď","‚Ėą‚Ėď‚ĖĄ‚ĖĄ‚Ėą‚Ėď‚ĖĄ‚ĖĄ‚Ėą‚Ėď"],"colors":["3b3b0707070707073b3b","3b3b0707070707073b3b","3b3b0707070707073b3b","38380707383807073838","38380707383807073838","38380707383807073838","38380707383807073838","38380707383807073838","38380707383807073838","38380707383807073838","38380303383803033838"]},"x":{"chars":["‚Ėí‚Ėď  ‚Ėą‚Ėą","‚ĖĎ‚Ėí  ‚Ėą‚Ėą"," ‚ĖĎ  ‚Ėď‚Ėą","    ‚Ėď‚Ėď","‚ĖĎ   ‚Ėą‚Ėď","‚ĖĎ‚ĖĎ  ‚Ėď‚Ėą","‚Ėí‚ĖĎ  ‚Ėí‚Ėď","‚ĖĄ‚Ėí‚ĖÄ‚ĖÄ‚ĖĎ‚ĖĄ","‚Ėď‚Ėí   ‚ĖĎ","‚Ėď‚Ėď  ‚ĖĎ ","‚Ėą‚Ėď  ‚Ėí‚ĖĎ"],"colors":["3b3b07073f0f","3b3b07073f3f","3b3b07073f3f","3b3b07073f3f","383807073b3f","383807073b3b","383807073b3b","033803033b03","38380707383b","383807073838","383807073838"]},"y":{"chars":["‚Ėí‚Ėď  ‚Ėą‚Ėą","‚ĖĎ‚Ėí  ‚Ėą‚Ėą"," ‚ĖĎ  ‚Ėď‚Ėą","    ‚Ėď‚Ėď","‚ĖĎ   ‚Ėą‚Ėď","‚ĖĎ‚ĖĎ  ‚Ėď‚Ėą","‚Ėí‚ĖĎ  ‚Ėí‚Ėď"," ‚ĖÄ‚ĖÄ‚ĖÄ‚ĖĎ ","‚Ėď‚Ėí   ‚ĖĎ","‚Ėď‚Ėď  ‚ĖĎ ","‚Ėą‚Ėď‚ĖĄ‚ĖĄ‚Ėí‚ĖÄ"],"colors":["3b3b07073f0f","3b3b07073f3f","3b3b07073f3f","3b3b07073f3f","383807073b3f","383807073b3b","383807073b3b","070303033b3b","38380707383b","383807073838","383808083803"]},"z":{"chars":["‚Ėą‚Ėą‚ĖÄ‚ĖÄ‚Ėď‚ĖĄ","‚Ėą‚Ėą  ‚Ėí‚ĖĎ","‚Ėą‚Ėď  ‚ĖĎ ","‚Ėď‚Ėď    ","‚Ėď‚Ėą   ‚ĖĎ","‚Ėą‚Ėď  ‚ĖĎ‚ĖĎ","    ‚ĖĎ‚Ėí","‚ĖĄ‚ĖĎ‚ĖÄ‚ĖÄ‚ĖÄ ","‚ĖĎ   ‚Ėí‚Ėď"," ‚ĖĎ  ‚Ėď‚Ėď","‚ĖÄ‚Ėí‚ĖĄ‚ĖĄ‚Ėď‚Ėą"],"colors":["0f3f0b0b3b03","3f3f07073b3b","3f3f07073b3b","3f3f07073b3b","3f3b07073838","3b3b07073838","070707073838","033b03030307","3b3807073838","383807073838","033808083838"]}}}
